{
  "bgm": [
    "BGM_06",
    "BGM_17"
  ],
  "bgp": [
    "BG_063_A0",
    "BG_189_A0",
    "BG_192_A0",
    "BG_BLACK"
  ],
  "egp": [],
  "cid": [
    "ENA",
    "MIN",
    "NAD",
    "RIN",
    "SAK"
  ],
  "label": [
    {
      "name": "SCR_L_YC_LYA_2_2_START",
      "line": 0
    }
  ],
  "message": [
    {
      "function": "XAUTOSAVE_SCENE",
      "argument": [],
      "name": "",
      "msgidx": -1,
      "voice": "",
      "vid": "",
      "value": "",
      "said": ""
    },
    {
      "function": "XCLR",
      "argument": [],
      "name": "",
      "msgidx": -1,
      "voice": "",
      "vid": "",
      "value": "",
      "said": ""
    },
    {
      "function": "XFADE",
      "argument": [
        "XFTS,MaskTexture.None,0",
        "XFOT,0.5"
      ],
      "name": "",
      "msgidx": -1,
      "voice": "",
      "vid": "",
      "value": "",
      "said": ""
    },
    {
      "function": "XWXB",
      "argument": [],
      "name": "",
      "msgidx": -1,
      "voice": "",
      "vid": "",
      "value": "",
      "said": ""
    },
    {
      "function": "SNSE",
      "argument": [
        "NSE_OFF",
        "0"
      ],
      "name": "",
      "msgidx": -1,
      "voice": "",
      "vid": "",
      "value": "",
      "said": ""
    },
    {
      "function": "XWXB",
      "argument": [],
      "name": "",
      "msgidx": -1,
      "voice": "",
      "vid": "",
      "value": "",
      "said": ""
    },
    {
      "function": "XLCYDRAW",
      "argument": [
        "XLCYLOAD,Lucy.Type.BACK,BG_BLACK",
        "XLCYFADE,0,0.001"
      ],
      "name": "",
      "msgidx": -1,
      "voice": "",
      "vid": "",
      "value": "",
      "said": ""
    },
    {
      "function": "XLCYDRAW",
      "argument": [
        "XLCYINIT",
        "XLCYFIND,FindType.SP_C",
        "XLCYLOAD,Lucy.Type.BUST,BU_OFF",
        "XLCYLOAD,Lucy.Type.SP_L,SP_OFF",
        "XLCYLOAD,Lucy.Type.SP_R,SP_OFF",
        "XLCYLOAD,Lucy.Type.SP_C,SP_OFF",
        "XLCYLOAD,Lucy.Type.MG_0,MG_OFF",
        "XLCYLOAD,Lucy.Type.MG_1,MG_OFF",
        "XLCYFADE,0,0.25"
      ],
      "name": "",
      "msgidx": -1,
      "voice": "",
      "vid": "",
      "value": "",
      "said": ""
    },
    {
      "function": "SBGM",
      "argument": [
        "BGM_OFF"
      ],
      "name": "",
      "msgidx": -1,
      "voice": "",
      "vid": "",
      "value": "",
      "said": ""
    },
    {
      "function": "SESE",
      "argument": [
        "ESE_OFF",
        "0"
      ],
      "name": "",
      "msgidx": -1,
      "voice": "",
      "vid": "",
      "value": "",
      "said": ""
    },
    {
      "function": "XMOF",
      "argument": [],
      "name": "",
      "msgidx": -1,
      "voice": "",
      "vid": "",
      "value": "",
      "said": ""
    },
    {
      "function": "XFADE",
      "argument": [
        "XFTS,MaskTexture.None,0",
        "XFIN,0.5"
      ],
      "name": "",
      "msgidx": -1,
      "voice": "",
      "vid": "",
      "value": "",
      "said": ""
    },
    {
      "function": "XLOGOIN",
      "argument": [],
      "name": "",
      "msgidx": -1,
      "voice": "",
      "vid": "",
      "value": "",
      "said": ""
    },
    {
      "function": "XLCYDRAW",
      "argument": [
        "XLCYLOAD,Lucy.Type.BACK,BG_192_A0",
        "XLCYFADE,0,0.25"
      ],
      "name": "",
      "msgidx": -1,
      "voice": "",
      "vid": "",
      "value": "",
      "said": ""
    },
    {
      "function": "XLOGOOUT",
      "argument": [],
      "name": "",
      "msgidx": -1,
      "voice": "",
      "vid": "",
      "value": "",
      "said": ""
    },
    {
      "function": "XMOF",
      "argument": [],
      "name": "",
      "msgidx": -1,
      "voice": "",
      "vid": "",
      "value": "",
      "said": ""
    },
    {
      "function": "XCLR",
      "argument": [],
      "name": "",
      "msgidx": -1,
      "voice": "",
      "vid": "",
      "value": "",
      "said": ""
    },
    {
      "function": "XCMNT",
      "argument": [
        "『Sedang mampir di Kafe Taman Fuefuki』"
      ],
      "name": "",
      "msgidx": -1,
      "voice": "",
      "vid": "",
      "value": "",
      "said": ""
    },
    {
      "function": "XFADE",
      "argument": [
        "XFTS,MaskTexture.None,0",
        "XFOT,0.5"
      ],
      "name": "",
      "msgidx": -1,
      "voice": "",
      "vid": "",
      "value": "",
      "said": ""
    },
    {
      "function": "XWXB",
      "argument": [],
      "name": "",
      "msgidx": -1,
      "voice": "",
      "vid": "",
      "value": "",
      "said": ""
    },
    {
      "function": "SNSE",
      "argument": [
        "NSE_OFF",
        "0"
      ],
      "name": "",
      "msgidx": -1,
      "voice": "",
      "vid": "",
      "value": "",
      "said": ""
    },
    {
      "function": "XWXB",
      "argument": [],
      "name": "",
      "msgidx": -1,
      "voice": "",
      "vid": "",
      "value": "",
      "said": ""
    },
    {
      "function": "XLCYDRAW",
      "argument": [
        "XLCYLOAD,Lucy.Type.BACK,BG_063_A0",
        "XLCYFADE,0,0.001"
      ],
      "name": "",
      "msgidx": -1,
      "voice": "",
      "vid": "",
      "value": "",
      "said": ""
    },
    {
      "function": "XLCYDRAW",
      "argument": [
        "XLCYINIT",
        "XLCYFIND,FindType.SP_C",
        "XLCYLOAD,Lucy.Type.BUST,BU_OFF",
        "XLCYLOAD,Lucy.Type.SP_L,SP_OFF",
        "XLCYLOAD,Lucy.Type.SP_R,SP_OFF",
        "XLCYLOAD,Lucy.Type.SP_C,SP_OFF",
        "XLCYLOAD,Lucy.Type.MG_0,MG_OFF",
        "XLCYLOAD,Lucy.Type.MG_1,MG_OFF",
        "XLCYFADE,0,0.25"
      ],
      "name": "",
      "msgidx": -1,
      "voice": "",
      "vid": "",
      "value": "",
      "said": ""
    },
    {
      "function": "SBGM",
      "argument": [
        "BGM_06"
      ],
      "name": "",
      "msgidx": -1,
      "voice": "",
      "vid": "",
      "value": "",
      "said": ""
    },
    {
      "function": "SESE",
      "argument": [
        "ESE_OFF",
        "0"
      ],
      "name": "",
      "msgidx": -1,
      "voice": "",
      "vid": "",
      "value": "",
      "said": ""
    },
    {
      "function": "XMON",
      "argument": [],
      "name": "",
      "msgidx": -1,
      "voice": "",
      "vid": "",
      "value": "",
      "said": ""
    },
    {
      "function": "XFADE",
      "argument": [
        "XFTS,MaskTexture.None,0",
        "XFIN,0.5"
      ],
      "name": "",
      "msgidx": -1,
      "voice": "",
      "vid": "",
      "value": "",
      "said": ""
    },
    {
      "function": "XCUTINSET",
      "argument": [
        "L1",
        "1",
        "NAD_DLC",
        "1",
        "-1",
        "-1",
        "NONE",
        "T_OFF",
        "A_NON",
        "CutinActive.V_ON"
      ],
      "name": "",
      "msgidx": -1,
      "voice": "",
      "vid": "",
      "value": "",
      "said": ""
    },
    {
      "function": "XCUTINDRAW",
      "argument": [],
      "name": "",
      "msgidx": -1,
      "voice": "",
      "vid": "",
      "value": "",
      "said": ""
    },
    {
      "function": "XMESS",
      "argument": [
        "Fruits Sundae-nya enak!"
      ],
      "name": "Kagamihara Nadeshiko",
      "msgidx": 0,
      "voice": "NAD_4033_0001",
      "vid": "VID_NAD",
      "value": "",
      "said": ""
    },
    {
      "function": "XWCR",
      "argument": [],
      "name": "",
      "msgidx": -1,
      "voice": "",
      "vid": "",
      "value": "",
      "said": ""
    },
    {
      "function": "XCUTINSET",
      "argument": [
        "R1",
        "2",
        "CHI_DLC",
        "1",
        "0",
        "-1",
        "NONE",
        "T_OFF",
        "A_NON",
        "CutinActive.V_ON"
      ],
      "name": "",
      "msgidx": -1,
      "voice": "",
      "vid": "",
      "value": "",
      "said": ""
    },
    {
      "function": "XCUTINDRAW",
      "argument": [],
      "name": "",
      "msgidx": -1,
      "voice": "",
      "vid": "",
      "value": "",
      "said": ""
    },
    {
      "function": "XMESS",
      "argument": [
        "Enak beud."
      ],
      "name": "Ōgaki Chiaki",
      "msgidx": 1,
      "voice": "CHI_1905_0002",
      "vid": "VID_CHI",
      "value": "",
      "said": ""
    },
    {
      "function": "XWCR",
      "argument": [],
      "name": "",
      "msgidx": -1,
      "voice": "",
      "vid": "",
      "value": "",
      "said": ""
    },
    {
      "function": "XCUTINSET",
      "argument": [
        "L1",
        "3",
        "AOI_DLC",
        "2",
        "0",
        "AOI_DLC",
        "NONE",
        "T_OFF",
        "A_NON",
        "CutinActive.V_ON"
      ],
      "name": "",
      "msgidx": -1,
      "voice": "",
      "vid": "",
      "value": "",
      "said": ""
    },
    {
      "function": "XCUTINDRAW",
      "argument": [],
      "name": "",
      "msgidx": -1,
      "voice": "",
      "vid": "",
      "value": "",
      "said": ""
    },
    {
      "function": "XMESS",
      "argument": [
        "Beud."
      ],
      "name": "Inuyama Aoi",
      "msgidx": 2,
      "voice": "AOI_1653_0003",
      "vid": "VID_AOI",
      "value": "",
      "said": ""
    },
    {
      "function": "XWCR",
      "argument": [],
      "name": "",
      "msgidx": -1,
      "voice": "",
      "vid": "",
      "value": "",
      "said": ""
    },
    {
      "function": "XCUTINCLEAR",
      "argument": [
        "4"
      ],
      "name": "",
      "msgidx": -1,
      "voice": "",
      "vid": "",
      "value": "",
      "said": ""
    },
    {
      "function": "XLCYDRAW",
      "argument": [
        "XLCYFIND,FindType.SP_L|FindType.SP_R",
        "XLCYLOAD,Lucy.Type.BUST,BU_OFF",
        "XLCYLOAD,Lucy.Type.SP_L,SP_RIN_CMP1_0_SML",
        "XLCYLOAD,Lucy.Type.SP_R,SP_ENA_CMM4_0_SML",
        "XLCYLOAD,Lucy.Type.SP_C,SP_OFF",
        "XLCYFADE,0,0.25"
      ],
      "name": "",
      "msgidx": -1,
      "voice": "",
      "vid": "",
      "value": "",
      "said": ""
    },
    {
      "function": "XMESS",
      "argument": [
        "Seperti yang diharapkan dari daerah",
        "penghasil buah. Buahnya begitu berair",
        "dan enak."
      ],
      "name": "Shima Rin",
      "msgidx": 3,
      "voice": "RIN_3203_0004",
      "vid": "VID_RIN",
      "value": "",
      "said": ""
    },
    {
      "function": "XWCR",
      "argument": [],
      "name": "",
      "msgidx": -1,
      "voice": "",
      "vid": "",
      "value": "",
      "said": ""
    },
    {
      "function": "XLCYDRAW",
      "argument": [
        "XLCYLOAD,Lucy.Type.BUST,BU_OFF",
        "XLCYLOAD,Lucy.Type.AUTO,SP_RIN_CMP1_0_NML",
        "XLCYFADE,0,0.25"
      ],
      "name": "",
      "msgidx": -1,
      "voice": "",
      "vid": "",
      "value": "",
      "said": ""
    },
    {
      "function": "XMESS",
      "argument": [
        "Apalagi katanya buahnya berbeda",
        "tergantung pada musimnya."
      ],
      "name": "Shima Rin",
      "msgidx": 4,
      "voice": "RIN_3204_0005",
      "vid": "VID_RIN",
      "value": "",
      "said": ""
    },
    {
      "function": "XWCR",
      "argument": [],
      "name": "",
      "msgidx": -1,
      "voice": "",
      "vid": "",
      "value": "",
      "said": ""
    },
    {
      "function": "XLCYDRAW",
      "argument": [
        "XLCYLOAD,Lucy.Type.BUST,BU_OFF",
        "XLCYLOAD,Lucy.Type.AUTO,SP_ENA_CMM4_0_LAU",
        "XLCYFADE,0,0.25"
      ],
      "name": "",
      "msgidx": -1,
      "voice": "",
      "vid": "",
      "value": "",
      "said": ""
    },
    {
      "function": "XMESS",
      "argument": [
        "Jadi ingin datang lagi setiap ganti musim ya."
      ],
      "name": "Saitō Ena",
      "msgidx": 5,
      "voice": "ENA_1184_0006",
      "vid": "VID_ENA",
      "value": "",
      "said": ""
    },
    {
      "function": "XWCR",
      "argument": [],
      "name": "",
      "msgidx": -1,
      "voice": "",
      "vid": "",
      "value": "",
      "said": ""
    },
    {
      "function": "XLCYDRAW",
      "argument": [
        "XLCYLOAD,Lucy.Type.BUST,BU_OFF",
        "XLCYLOAD,Lucy.Type.AUTO,SP_ENA_CMM4_0_CON",
        "XLCYFADE,0,0.25"
      ],
      "name": "",
      "msgidx": -1,
      "voice": "",
      "vid": "",
      "value": "",
      "said": ""
    },
    {
      "function": "XMESS",
      "argument": [
        "Hanya aku yang makan enak gini tuh,",
        "jadi merasa bersalah pada Chikuwa."
      ],
      "name": "Saitō Ena",
      "msgidx": 6,
      "voice": "ENA_1185_0007",
      "vid": "VID_ENA",
      "value": "",
      "said": ""
    },
    {
      "function": "XWCR",
      "argument": [],
      "name": "",
      "msgidx": -1,
      "voice": "",
      "vid": "",
      "value": "",
      "said": ""
    },
    {
      "function": "XLCYDRAW",
      "argument": [
        "XLCYLOAD,Lucy.Type.BUST,BU_OFF",
        "XLCYLOAD,Lucy.Type.AUTO,SP_ENA_CMM4_0_NML",
        "XLCYFADE,0,0.25"
      ],
      "name": "",
      "msgidx": -1,
      "voice": "",
      "vid": "",
      "value": "",
      "said": ""
    },
    {
      "function": "XMESS",
      "argument": [
        "Nanti aku harus menghiburnya",
        "dengan memberinya camilan."
      ],
      "name": "Saitō Ena",
      "msgidx": 7,
      "voice": "ENA_1186_0008",
      "vid": "VID_ENA",
      "value": "",
      "said": ""
    },
    {
      "function": "XWCR",
      "argument": [],
      "name": "",
      "msgidx": -1,
      "voice": "",
      "vid": "",
      "value": "",
      "said": ""
    },
    {
      "function": "XLCYDRAW",
      "argument": [
        "XLCYLOAD,Lucy.Type.BUST,BU_OFF",
        "XLCYLOAD,Lucy.Type.AUTO,SP_RIN_CMP1_0_SML",
        "XLCYFADE,0,0.25"
      ],
      "name": "",
      "msgidx": -1,
      "voice": "",
      "vid": "",
      "value": "",
      "said": ""
    },
    {
      "function": "XMESS",
      "argument": [
        "Itu bagus."
      ],
      "name": "Shima Rin",
      "msgidx": 8,
      "voice": "RIN_3205_0009",
      "vid": "VID_RIN",
      "value": "",
      "said": ""
    },
    {
      "function": "XWCR",
      "argument": [],
      "name": "",
      "msgidx": -1,
      "voice": "",
      "vid": "",
      "value": "",
      "said": ""
    },
    {
      "function": "XLCYDRAW",
      "argument": [
        "XLCYFIND,FindType.SP_C",
        "XLCYLOAD,Lucy.Type.BUST,BU_OFF",
        "XLCYLOAD,Lucy.Type.SP_L,SP_OFF",
        "XLCYLOAD,Lucy.Type.SP_R,SP_OFF",
        "XLCYLOAD,Lucy.Type.SP_C,SP_RIN_CMP1_0_NML",
        "XLCYFADE,0,0.25"
      ],
      "name": "",
      "msgidx": -1,
      "voice": "",
      "vid": "",
      "value": "",
      "said": ""
    },
    {
      "function": "XMESS",
      "argument": [
        "Btw, tadi aku dengar dari Sakura-san."
      ],
      "name": "Shima Rin",
      "msgidx": 9,
      "voice": "RIN_3206_0010",
      "vid": "VID_RIN",
      "value": "",
      "said": ""
    },
    {
      "function": "XWCR",
      "argument": [],
      "name": "",
      "msgidx": -1,
      "voice": "",
      "vid": "",
      "value": "",
      "said": ""
    },
    {
      "function": "XLCYDRAW",
      "argument": [
        "XLCYLOAD,Lucy.Type.BUST,BU_OFF",
        "XLCYLOAD,Lucy.Type.AUTO,SP_RIN_CMP1_0_NML",
        "XLCYFADE,0,0.25"
      ],
      "name": "",
      "msgidx": -1,
      "voice": "",
      "vid": "",
      "value": "",
      "said": ""
    },
    {
      "function": "XMESS",
      "argument": [
        "Katanya pemandangan malam yang terlihat",
        "dari taman ini sangat spektakuler & terkenal."
      ],
      "name": "Shima Rin",
      "msgidx": 10,
      "voice": "RIN_3207_0011",
      "vid": "VID_RIN",
      "value": "",
      "said": ""
    },
    {
      "function": "XWCR",
      "argument": [],
      "name": "",
      "msgidx": -1,
      "voice": "",
      "vid": "",
      "value": "",
      "said": ""
    },
    {
      "function": "XLCYDRAW",
      "argument": [
        "XLCYLOAD,Lucy.Type.BUST,BU_OFF",
        "XLCYLOAD,Lucy.Type.AUTO,SP_NAD_CPB1_0_LAU",
        "XLCYFADE,0,0.25"
      ],
      "name": "",
      "msgidx": -1,
      "voice": "",
      "vid": "",
      "value": "",
      "said": ""
    },
    {
      "function": "XMESS",
      "argument": [
        "Hee, aku jadi ingin melihatnya."
      ],
      "name": "Kagamihara Nadeshiko",
      "msgidx": 11,
      "voice": "NAD_4034_0012",
      "vid": "VID_NAD",
      "value": "",
      "said": ""
    },
    {
      "function": "XWCR",
      "argument": [],
      "name": "",
      "msgidx": -1,
      "voice": "",
      "vid": "",
      "value": "",
      "said": ""
    },
    {
      "function": "XLCYDRAW",
      "argument": [
        "XLCYLOAD,Lucy.Type.BUST,BU_OFF",
        "XLCYLOAD,Lucy.Type.AUTO,SP_SAK_CAM2_0_NML",
        "XLCYFADE,0,0.25"
      ],
      "name": "",
      "msgidx": -1,
      "voice": "",
      "vid": "",
      "value": "",
      "said": ""
    },
    {
      "function": "XMESS",
      "argument": [
        "Maaf menunggu."
      ],
      "name": "Kagamihara Sakura",
      "msgidx": 12,
      "voice": "SAK_0601_0013",
      "vid": "VID_SAK",
      "value": "",
      "said": ""
    },
    {
      "function": "XWCR",
      "argument": [],
      "name": "",
      "msgidx": -1,
      "voice": "",
      "vid": "",
      "value": "",
      "said": ""
    },
    {
      "function": "XLCYDRAW",
      "argument": [
        "XLCYFIND,FindType.SP_L|FindType.SP_R",
        "XLCYLOAD,Lucy.Type.BUST,BU_OFF",
        "XLCYLOAD,Lucy.Type.SP_L,SP_NAD_CPB1_0_NML",
        "XLCYLOAD,Lucy.Type.SP_R,SP_SAK_CAM2_0_NML",
        "XLCYLOAD,Lucy.Type.SP_C,SP_OFF",
        "XLCYFADE,0,0.25"
      ],
      "name": "",
      "msgidx": -1,
      "voice": "",
      "vid": "",
      "value": "",
      "said": ""
    },
    {
      "function": "XMESS",
      "argument": [
        "Ah, kakak.",
        "Ternyata sangat memakan waktu ya."
      ],
      "name": "Kagamihara Nadeshiko",
      "msgidx": 13,
      "voice": "NAD_4035_0014",
      "vid": "VID_NAD",
      "value": "",
      "said": ""
    },
    {
      "function": "XWCR",
      "argument": [],
      "name": "",
      "msgidx": -1,
      "voice": "",
      "vid": "",
      "value": "",
      "said": ""
    },
    {
      "function": "XLCYDRAW",
      "argument": [
        "XLCYLOAD,Lucy.Type.BUST,BU_OFF",
        "XLCYLOAD,Lucy.Type.AUTO,SP_SAK_CAM2_0_CON",
        "XLCYFADE,0,0.25"
      ],
      "name": "",
      "msgidx": -1,
      "voice": "",
      "vid": "",
      "value": "",
      "said": ""
    },
    {
      "function": "XMESS",
      "argument": [
        "Mungkin karena aku dan Toba-sensei",
        "memesan hal yang berbeda dari kalian,",
        "makanya hanya kami saja yang agak lama."
      ],
      "name": "Kagamihara Sakura",
      "msgidx": 14,
      "voice": "SAK_0602_0015",
      "vid": "VID_SAK",
      "value": "",
      "said": ""
    },
    {
      "function": "XWCR",
      "argument": [],
      "name": "",
      "msgidx": -1,
      "voice": "",
      "vid": "",
      "value": "",
      "said": ""
    },
    {
      "function": "XLCYDRAW",
      "argument": [
        "XLCYFIND,FindType.SP_L|FindType.SP_R",
        "XLCYLOAD,Lucy.Type.BUST,BU_OFF",
        "XLCYLOAD,Lucy.Type.SP_L,SP_MIN_CMM_0_LAU",
        "XLCYLOAD,Lucy.Type.SP_C,SP_OFF",
        "XLCYFADE,0,0.25"
      ],
      "name": "",
      "msgidx": -1,
      "voice": "",
      "vid": "",
      "value": "",
      "said": ""
    },
    {
      "function": "XMESS",
      "argument": [
        "Tapi, ini masih bisa dimaklumi lah.",
        "Nah, ayo kita santap."
      ],
      "name": "Toba Minami",
      "msgidx": 15,
      "voice": "MIN_1023_0016",
      "vid": "VID_MIN",
      "value": "",
      "said": ""
    },
    {
      "function": "XWCR",
      "argument": [],
      "name": "",
      "msgidx": -1,
      "voice": "",
      "vid": "",
      "value": "",
      "said": ""
    },
    {
      "function": "SBGM",
      "argument": [
        "BGM_OFF"
      ],
      "name": "",
      "msgidx": -1,
      "voice": "",
      "vid": "",
      "value": "",
      "said": ""
    },
    {
      "function": "XCUTINSET",
      "argument": [
        "R1",
        "2",
        "CHI_SUP",
        "1",
        "0",
        "-1",
        "NONE",
        "T_OFF",
        "A_NON",
        "CutinActive.V_ON"
      ],
      "name": "",
      "msgidx": -1,
      "voice": "",
      "vid": "",
      "value": "",
      "said": ""
    },
    {
      "function": "XCUTINDRAW",
      "argument": [],
      "name": "",
      "msgidx": -1,
      "voice": "",
      "vid": "",
      "value": "",
      "said": ""
    },
    {
      "function": "XMESS",
      "argument": [
        "Aaah?!",
        "I-itukan.....!"
      ],
      "name": "Ōgaki Chiaki",
      "msgidx": 16,
      "voice": "CHI_1906_0017",
      "vid": "VID_CHI",
      "value": "",
      "said": ""
    },
    {
      "function": "XWCR",
      "argument": [],
      "name": "",
      "msgidx": -1,
      "voice": "",
      "vid": "",
      "value": "",
      "said": ""
    },
    {
      "function": "SBGM",
      "argument": [
        "BGM_17"
      ],
      "name": "",
      "msgidx": -1,
      "voice": "",
      "vid": "",
      "value": "",
      "said": ""
    },
    {
      "function": "XCUTINSET",
      "argument": [
        "L1",
        "3",
        "AOI_NML",
        "2",
        "0",
        "AOI_NML",
        "NONE",
        "T_OFF",
        "A_NON",
        "CutinActive.V_ON"
      ],
      "name": "",
      "msgidx": -1,
      "voice": "",
      "vid": "",
      "value": "",
      "said": ""
    },
    {
      "function": "XCUTINDRAW",
      "argument": [],
      "name": "",
      "msgidx": -1,
      "voice": "",
      "vid": "",
      "value": "",
      "said": ""
    },
    {
      "function": "XMESS",
      "argument": [
        "Aki, ada apa?"
      ],
      "name": "Inuyama Aoi",
      "msgidx": 17,
      "voice": "AOI_1654_0018",
      "vid": "VID_AOI",
      "value": "",
      "said": ""
    },
    {
      "function": "XWCR",
      "argument": [],
      "name": "",
      "msgidx": -1,
      "voice": "",
      "vid": "",
      "value": "",
      "said": ""
    },
    {
      "function": "XCUTINSET",
      "argument": [
        "R1",
        "2",
        "CHI_SUP",
        "1",
        "0",
        "-1",
        "NONE",
        "T_OFF",
        "A_SHVR",
        "CutinActive.V_ON"
      ],
      "name": "",
      "msgidx": -1,
      "voice": "",
      "vid": "",
      "value": "",
      "said": ""
    },
    {
      "function": "XCUTINDRAW",
      "argument": [],
      "name": "",
      "msgidx": -1,
      "voice": "",
      "vid": "",
      "value": "",
      "said": ""
    },
    {
      "function": "XMESS",
      "argument": [
        "Lihatlah apa yang dipesan mereka!"
      ],
      "name": "Ōgaki Chiaki",
      "msgidx": 18,
      "voice": "CHI_1907_0019",
      "vid": "VID_CHI",
      "value": "",
      "said": ""
    },
    {
      "function": "XWCR",
      "argument": [],
      "name": "",
      "msgidx": -1,
      "voice": "",
      "vid": "",
      "value": "",
      "said": ""
    },
    {
      "function": "XCUTINSET",
      "argument": [
        "R1",
        "2",
        "CHI_EXC",
        "1",
        "0",
        "-1",
        "NONE",
        "T_OFF",
        "A_SHVR",
        "CutinActive.V_ON"
      ],
      "name": "",
      "msgidx": -1,
      "voice": "",
      "vid": "",
      "value": "",
      "said": ""
    },
    {
      "function": "XCUTINDRAW",
      "argument": [],
      "name": "",
      "msgidx": -1,
      "voice": "",
      "vid": "",
      "value": "",
      "said": ""
    },
    {
      "function": "XMESS",
      "argument": [
        "Itu.... Parfait stroberi musiman",
        "yang paling mahal di kafe ini!"
      ],
      "name": "Ōgaki Chiaki",
      "msgidx": 19,
      "voice": "CHI_1908_0020",
      "vid": "VID_CHI",
      "value": "",
      "said": ""
    },
    {
      "function": "XWCR",
      "argument": [],
      "name": "",
      "msgidx": -1,
      "voice": "",
      "vid": "",
      "value": "",
      "said": ""
    },
    {
      "function": "XCUTINSET",
      "argument": [
        "L1",
        "3",
        "AOI_SUP",
        "2",
        "0",
        "AOI_SUP",
        "NONE",
        "T_OFF",
        "A_SHVR",
        "CutinActive.V_ON"
      ],
      "name": "",
      "msgidx": -1,
      "voice": "",
      "vid": "",
      "value": "",
      "said": ""
    },
    {
      "function": "XCUTINDRAW",
      "argument": [],
      "name": "",
      "msgidx": -1,
      "voice": "",
      "vid": "",
      "value": "",
      "said": ""
    },
    {
      "function": "XMESS",
      "argument": [
        "Apa kau bilang?!"
      ],
      "name": "Inuyama Aoi",
      "msgidx": 20,
      "voice": "AOI_1655_0021",
      "vid": "VID_AOI",
      "value": "",
      "said": ""
    },
    {
      "function": "XWCR",
      "argument": [],
      "name": "",
      "msgidx": -1,
      "voice": "",
      "vid": "",
      "value": "",
      "said": ""
    },
    {
      "function": "XCUTINSET",
      "argument": [
        "L2",
        "4",
        "ENA_SUP",
        "1",
        "0",
        "-1",
        "NONE",
        "T_OFF",
        "A_SHVR",
        "CutinActive.V_ON"
      ],
      "name": "",
      "msgidx": -1,
      "voice": "",
      "vid": "",
      "value": "",
      "said": ""
    },
    {
      "function": "XCUTINDRAW",
      "argument": [],
      "name": "",
      "msgidx": -1,
      "voice": "",
      "vid": "",
      "value": "",
      "said": ""
    },
    {
      "function": "XMESS",
      "argument": [
        "Hal yang begitu mahal...",
        "Jadi inilah kekuatan dompet orang dewasa!"
      ],
      "name": "Saitō Ena",
      "msgidx": 21,
      "voice": "ENA_1187_0022",
      "vid": "VID_ENA",
      "value": "",
      "said": ""
    },
    {
      "function": "XWCR",
      "argument": [],
      "name": "",
      "msgidx": -1,
      "voice": "",
      "vid": "",
      "value": "",
      "said": ""
    },
    {
      "function": "XFADE",
      "argument": [
        "XFTS,MaskTexture.None,0",
        "XFOT,0.5"
      ],
      "name": "",
      "msgidx": -1,
      "voice": "",
      "vid": "",
      "value": "",
      "said": ""
    },
    {
      "function": "XWXB",
      "argument": [],
      "name": "",
      "msgidx": -1,
      "voice": "",
      "vid": "",
      "value": "",
      "said": ""
    },
    {
      "function": "SNSE",
      "argument": [
        "NSE_OFF",
        "0"
      ],
      "name": "",
      "msgidx": -1,
      "voice": "",
      "vid": "",
      "value": "",
      "said": ""
    },
    {
      "function": "XWXB",
      "argument": [],
      "name": "",
      "msgidx": -1,
      "voice": "",
      "vid": "",
      "value": "",
      "said": ""
    },
    {
      "function": "XLCYDRAW",
      "argument": [
        "XLCYLOAD,Lucy.Type.BACK,BG_189_A0",
        "XLCYFADE,0,0.001"
      ],
      "name": "",
      "msgidx": -1,
      "voice": "",
      "vid": "",
      "value": "",
      "said": ""
    },
    {
      "function": "XLCYDRAW",
      "argument": [
        "XLCYINIT",
        "XLCYFIND,FindType.SP_C",
        "XLCYLOAD,Lucy.Type.BUST,BU_OFF",
        "XLCYLOAD,Lucy.Type.SP_L,SP_OFF",
        "XLCYLOAD,Lucy.Type.SP_R,SP_OFF",
        "XLCYLOAD,Lucy.Type.SP_C,SP_OFF",
        "XLCYLOAD,Lucy.Type.MG_0,MG_OFF",
        "XLCYLOAD,Lucy.Type.MG_1,MG_OFF",
        "XLCYFADE,0,0.25"
      ],
      "name": "",
      "msgidx": -1,
      "voice": "",
      "vid": "",
      "value": "",
      "said": ""
    },
    {
      "function": "SBGM",
      "argument": [
        "BGM_SAME"
      ],
      "name": "",
      "msgidx": -1,
      "voice": "",
      "vid": "",
      "value": "",
      "said": ""
    },
    {
      "function": "SESE",
      "argument": [
        "ESE_OFF",
        "0"
      ],
      "name": "",
      "msgidx": -1,
      "voice": "",
      "vid": "",
      "value": "",
      "said": ""
    },
    {
      "function": "XMON",
      "argument": [],
      "name": "",
      "msgidx": -1,
      "voice": "",
      "vid": "",
      "value": "",
      "said": ""
    },
    {
      "function": "XFADE",
      "argument": [
        "XFTS,MaskTexture.None,0",
        "XFIN,0.5"
      ],
      "name": "",
      "msgidx": -1,
      "voice": "",
      "vid": "",
      "value": "",
      "said": ""
    },
    {
      "function": "XMESS",
      "argument": [
        "Lagian....",
        "Kalian terlalu ribut."
      ],
      "name": "Shima Rin",
      "msgidx": 22,
      "voice": "RIN_3208_0023",
      "vid": "VID_RIN",
      "value": "",
      "said": ""
    },
    {
      "function": "XWCR",
      "argument": [],
      "name": "",
      "msgidx": -1,
      "voice": "",
      "vid": "",
      "value": "",
      "said": ""
    },
    {
      "function": "XMESS",
      "argument": [
        "Ehehehehe....."
      ],
      "name": "Kagamihara Nadeshiko",
      "msgidx": 23,
      "voice": "NAD_4036_0024",
      "vid": "VID_NAD",
      "value": "",
      "said": ""
    },
    {
      "function": "XWAI",
      "argument": [],
      "name": "",
      "msgidx": -1,
      "voice": "",
      "vid": "",
      "value": "",
      "said": ""
    },
    {
      "function": "XFADE",
      "argument": [
        "XFED,0.5"
      ],
      "name": "",
      "msgidx": -1,
      "voice": "",
      "vid": "",
      "value": "",
      "said": ""
    },
    {
      "function": "XCLR",
      "argument": [],
      "name": "",
      "msgidx": -1,
      "voice": "",
      "vid": "",
      "value": "",
      "said": ""
    },
    {
      "function": "XEOS",
      "argument": [],
      "name": "",
      "msgidx": -1,
      "voice": "",
      "vid": "",
      "value": "",
      "said": ""
    }
  ]
}