{
  "bgm": [
    "BGM_06",
    "BGM_10"
  ],
  "bgp": [
    "BG_124_C0",
    "BG_189_C0"
  ],
  "egp": [],
  "cid": [
    "ENA",
    "NAD",
    "RIN"
  ],
  "label": [
    {
      "name": "SCR_L_YC_W2B_5_3_START",
      "line": 0
    }
  ],
  "message": [
    {
      "function": "XAUTOSAVE_SCENE",
      "argument": [],
      "name": "",
      "msgidx": -1,
      "voice": "",
      "vid": "",
      "value": "",
      "said": ""
    },
    {
      "function": "XCLR",
      "argument": [],
      "name": "",
      "msgidx": -1,
      "voice": "",
      "vid": "",
      "value": "",
      "said": ""
    },
    {
      "function": "XFADE",
      "argument": [
        "XFTS,MaskTexture.None,0",
        "XFOT,0.5"
      ],
      "name": "",
      "msgidx": -1,
      "voice": "",
      "vid": "",
      "value": "",
      "said": ""
    },
    {
      "function": "XWXB",
      "argument": [],
      "name": "",
      "msgidx": -1,
      "voice": "",
      "vid": "",
      "value": "",
      "said": ""
    },
    {
      "function": "SNSE",
      "argument": [
        "NSE_OFF",
        "0"
      ],
      "name": "",
      "msgidx": -1,
      "voice": "",
      "vid": "",
      "value": "",
      "said": ""
    },
    {
      "function": "XWXB",
      "argument": [],
      "name": "",
      "msgidx": -1,
      "voice": "",
      "vid": "",
      "value": "",
      "said": ""
    },
    {
      "function": "XLCYDRAW",
      "argument": [
        "XLCYLOAD,Lucy.Type.BACK,BG_124_C0",
        "XLCYFADE,0,0.001"
      ],
      "name": "",
      "msgidx": -1,
      "voice": "",
      "vid": "",
      "value": "",
      "said": ""
    },
    {
      "function": "XLCYDRAW",
      "argument": [
        "XLCYFIND,FindType.SP_C",
        "XLCYLOAD,Lucy.Type.BUST,BU_OFF",
        "XLCYLOAD,Lucy.Type.SP_L,SP_OFF",
        "XLCYLOAD,Lucy.Type.SP_R,SP_OFF",
        "XLCYLOAD,Lucy.Type.SP_C,SP_RIN_CMM5_0_NML",
        "XLCYFADE,0,0.25"
      ],
      "name": "",
      "msgidx": -1,
      "voice": "",
      "vid": "",
      "value": "",
      "said": ""
    },
    {
      "function": "SBGM",
      "argument": [
        "BGM_06"
      ],
      "name": "",
      "msgidx": -1,
      "voice": "",
      "vid": "",
      "value": "",
      "said": ""
    },
    {
      "function": "SESE",
      "argument": [
        "ESE_OFF",
        "0"
      ],
      "name": "",
      "msgidx": -1,
      "voice": "",
      "vid": "",
      "value": "",
      "said": ""
    },
    {
      "function": "XMON",
      "argument": [],
      "name": "",
      "msgidx": -1,
      "voice": "",
      "vid": "",
      "value": "",
      "said": ""
    },
    {
      "function": "XFADE",
      "argument": [
        "XFTS,MaskTexture.None,0",
        "XFIN,0.5"
      ],
      "name": "",
      "msgidx": -1,
      "voice": "",
      "vid": "",
      "value": "",
      "said": ""
    },
    {
      "function": "XMESS",
      "argument": [
        "Makan malam hari ini akan membuat",
        "resep modifikasi menggunakan",
        "Hot Sand Maker."
      ],
      "name": "Shima Rin",
      "msgidx": 0,
      "voice": "RIN_2304_0001",
      "vid": "VID_RIN",
      "value": "",
      "said": ""
    },
    {
      "function": "XWCR",
      "argument": [],
      "name": "",
      "msgidx": -1,
      "voice": "",
      "vid": "",
      "value": "",
      "said": ""
    },
    {
      "function": "XLCYDRAW",
      "argument": [
        "XLCYLOAD,Lucy.Type.BUST,BU_OFF",
        "XLCYLOAD,Lucy.Type.AUTO,SP_ENA_CMM4_0_BSM_A",
        "XLCYFADE,0,0.25"
      ],
      "name": "",
      "msgidx": -1,
      "voice": "",
      "vid": "",
      "value": "",
      "said": ""
    },
    {
      "function": "XMESS",
      "argument": [
        "Hanya menghimpit Butaman dengan",
        "Hot Sand Maker saja kan ya?"
      ],
      "name": "Saitō Ena",
      "msgidx": 1,
      "voice": "ENA_0672_0002",
      "vid": "VID_ENA",
      "value": "",
      "said": ""
    },
    {
      "function": "XWCR",
      "argument": [],
      "name": "",
      "msgidx": -1,
      "voice": "",
      "vid": "",
      "value": "",
      "said": ""
    },
    {
      "function": "XLCYDRAW",
      "argument": [
        "XLCYLOAD,Lucy.Type.BUST,BU_OFF",
        "XLCYLOAD,Lucy.Type.AUTO,SP_RIN_CMM5_0_SML",
        "XLCYFADE,0,0.25"
      ],
      "name": "",
      "msgidx": -1,
      "voice": "",
      "vid": "",
      "value": "",
      "said": ""
    },
    {
      "function": "XMESS",
      "argument": [
        "Sudah mudah, enak pula.",
        "Benar-benar resep yang luar biasa."
      ],
      "name": "Shima Rin",
      "msgidx": 2,
      "voice": "RIN_2305_0003",
      "vid": "VID_RIN",
      "value": "",
      "said": ""
    },
    {
      "function": "XWCR",
      "argument": [],
      "name": "",
      "msgidx": -1,
      "voice": "",
      "vid": "",
      "value": "",
      "said": ""
    },
    {
      "function": "XLCYDRAW",
      "argument": [
        "XLCYLOAD,Lucy.Type.BUST,BU_OFF",
        "XLCYLOAD,Lucy.Type.AUTO,SP_NAD_CMB1_0_SML",
        "XLCYFADE,0,0.25"
      ],
      "name": "",
      "msgidx": -1,
      "voice": "",
      "vid": "",
      "value": "",
      "said": ""
    },
    {
      "function": "XMESS",
      "argument": [
        "Mfu, aku ingin segera memakannya."
      ],
      "name": "Kagamihara Nadeshiko",
      "msgidx": 3,
      "voice": "NAD_2730_0004",
      "vid": "VID_NAD",
      "value": "",
      "said": ""
    },
    {
      "function": "XWCR",
      "argument": [],
      "name": "",
      "msgidx": -1,
      "voice": "",
      "vid": "",
      "value": "",
      "said": ""
    },
    {
      "function": "XLCYDRAW",
      "argument": [
        "XLCYFIND,FindType.SP_L|FindType.SP_R",
        "XLCYLOAD,Lucy.Type.BUST,BU_OFF",
        "XLCYLOAD,Lucy.Type.SP_L,SP_RIN_CMM5_0_NML",
        "XLCYLOAD,Lucy.Type.SP_R,SP_NAD_CMB1_0_SML",
        "XLCYLOAD,Lucy.Type.SP_C,SP_OFF",
        "XLCYFADE,0,0.25"
      ],
      "name": "",
      "msgidx": -1,
      "voice": "",
      "vid": "",
      "value": "",
      "said": ""
    },
    {
      "function": "XMESS",
      "argument": [
        "Oh iya, bukankah kau membeli",
        "banyak camilan, Nadeshiko?"
      ],
      "name": "Shima Rin",
      "msgidx": 4,
      "voice": "RIN_2306_0005",
      "vid": "VID_RIN",
      "value": "",
      "said": ""
    },
    {
      "function": "XWCR",
      "argument": [],
      "name": "",
      "msgidx": -1,
      "voice": "",
      "vid": "",
      "value": "",
      "said": ""
    },
    {
      "function": "XLCYDRAW",
      "argument": [
        "XLCYLOAD,Lucy.Type.BUST,BU_OFF",
        "XLCYLOAD,Lucy.Type.AUTO,SP_NAD_CMB1_0_SUP",
        "XLCYFADE,0,0.25"
      ],
      "name": "",
      "msgidx": -1,
      "voice": "",
      "vid": "",
      "value": "",
      "said": ""
    },
    {
      "function": "XMESS",
      "argument": [
        "Aah, iya sih, aku terkejut saat",
        "mengeluarkannya dari barang bawaan,",
        "plastiknya jadi kembung."
      ],
      "name": "Kagamihara Nadeshiko",
      "msgidx": 5,
      "voice": "NAD_2731_0006",
      "vid": "VID_NAD",
      "value": "",
      "said": ""
    },
    {
      "function": "XWCR",
      "argument": [],
      "name": "",
      "msgidx": -1,
      "voice": "",
      "vid": "",
      "value": "",
      "said": ""
    },
    {
      "function": "XLCYDRAW",
      "argument": [
        "XLCYFIND,FindType.SP_L|FindType.SP_R",
        "XLCYLOAD,Lucy.Type.BUST,BU_OFF",
        "XLCYLOAD,Lucy.Type.SP_L,SP_ENA_CMM4_0_SML",
        "XLCYLOAD,Lucy.Type.SP_C,SP_OFF",
        "XLCYFADE,0,0.25"
      ],
      "name": "",
      "msgidx": -1,
      "voice": "",
      "vid": "",
      "value": "",
      "said": ""
    },
    {
      "function": "XMESS",
      "argument": [
        "Karena di dataran tinggi itu tekanan",
        "udaranya rendah, jadinya begitu deh."
      ],
      "name": "Saitō Ena",
      "msgidx": 6,
      "voice": "ENA_0673_0007",
      "vid": "VID_ENA",
      "value": "",
      "said": ""
    },
    {
      "function": "XWCR",
      "argument": [],
      "name": "",
      "msgidx": -1,
      "voice": "",
      "vid": "",
      "value": "",
      "said": ""
    },
    {
      "function": "XLCYDRAW",
      "argument": [
        "XLCYLOAD,Lucy.Type.BUST,BU_OFF",
        "XLCYLOAD,Lucy.Type.AUTO,SP_NAD_CMB1_0_LAU",
        "XLCYFADE,0,0.25"
      ],
      "name": "",
      "msgidx": -1,
      "voice": "",
      "vid": "",
      "value": "",
      "said": ""
    },
    {
      "function": "XMESS",
      "argument": [
        "Hee.",
        "Aku tidak terlalu mengerti,",
        "tapi keren ya."
      ],
      "name": "Kagamihara Nadeshiko",
      "msgidx": 7,
      "voice": "NAD_2732_0008",
      "vid": "VID_NAD",
      "value": "",
      "said": ""
    },
    {
      "function": "XWCR",
      "argument": [],
      "name": "",
      "msgidx": -1,
      "voice": "",
      "vid": "",
      "value": "",
      "said": ""
    },
    {
      "function": "XLCYDRAW",
      "argument": [
        "XLCYFIND,FindType.SP_C",
        "XLCYLOAD,Lucy.Type.BUST,BU_RIN_CMM5_0_NML",
        "XLCYLOAD,Lucy.Type.SP_L,SP_OFF",
        "XLCYLOAD,Lucy.Type.SP_R,SP_OFF",
        "XLCYLOAD,Lucy.Type.SP_C,SP_OFF",
        "XLCYFADE,0,0.25"
      ],
      "name": "",
      "msgidx": -1,
      "voice": "",
      "vid": "",
      "value": "",
      "said": ""
    },
    {
      "function": "XMESS",
      "argument": [
        "Nah, kumulai ya.",
        "Oleskan mentega pada kedua sisi",
        "Hot Sand Maker..."
      ],
      "name": "Shima Rin",
      "msgidx": 8,
      "voice": "RIN_2307_0009",
      "vid": "VID_RIN",
      "value": "",
      "said": ""
    },
    {
      "function": "XWCR",
      "argument": [],
      "name": "",
      "msgidx": -1,
      "voice": "",
      "vid": "",
      "value": "",
      "said": ""
    },
    {
      "function": "XLCYDRAW",
      "argument": [
        "XLCYFIND,FindType.SP_C",
        "XLCYLOAD,Lucy.Type.BUST,BU_RIN_CMM5_0_SML",
        "XLCYLOAD,Lucy.Type.SP_L,SP_OFF",
        "XLCYLOAD,Lucy.Type.SP_R,SP_OFF",
        "XLCYLOAD,Lucy.Type.SP_C,SP_OFF",
        "XLCYFADE,0,0.25"
      ],
      "name": "",
      "msgidx": -1,
      "voice": "",
      "vid": "",
      "value": "",
      "said": ""
    },
    {
      "function": "XMESS",
      "argument": [
        "Himpit Butaman yang dibeli",
        "di minimarket lalu tekan."
      ],
      "name": "Shima Rin",
      "msgidx": 9,
      "voice": "RIN_2308_0010",
      "vid": "VID_RIN",
      "value": "",
      "said": ""
    },
    {
      "function": "XWCR",
      "argument": [],
      "name": "",
      "msgidx": -1,
      "voice": "",
      "vid": "",
      "value": "",
      "said": ""
    },
    {
      "function": "SNSE",
      "argument": [
        "NSE_013",
        "0"
      ],
      "name": "",
      "msgidx": -1,
      "voice": "",
      "vid": "",
      "value": "",
      "said": ""
    },
    {
      "function": "XWTM",
      "argument": [
        "0.066"
      ],
      "name": "",
      "msgidx": -1,
      "voice": "",
      "vid": "",
      "value": "",
      "said": ""
    },
    {
      "function": "XWXB",
      "argument": [],
      "name": "",
      "msgidx": -1,
      "voice": "",
      "vid": "",
      "value": "",
      "said": ""
    },
    {
      "function": "XLCYDRAW",
      "argument": [
        "XLCYFIND,FindType.SP_C",
        "XLCYLOAD,Lucy.Type.BUST,BU_RIN_CMM5_0_SER",
        "XLCYLOAD,Lucy.Type.SP_L,SP_OFF",
        "XLCYLOAD,Lucy.Type.SP_R,SP_OFF",
        "XLCYLOAD,Lucy.Type.SP_C,SP_OFF",
        "XLCYFADE,0,0.25"
      ],
      "name": "",
      "msgidx": -1,
      "voice": "",
      "vid": "",
      "value": "",
      "said": ""
    },
    {
      "function": "XMESS",
      "argument": [
        "Panggang hingga kecoklatan..."
      ],
      "name": "Shima Rin",
      "msgidx": 10,
      "voice": "RIN_2309_0011",
      "vid": "VID_RIN",
      "value": "",
      "said": ""
    },
    {
      "function": "XWCR",
      "argument": [],
      "name": "",
      "msgidx": -1,
      "voice": "",
      "vid": "",
      "value": "",
      "said": ""
    },
    {
      "function": "SNSE",
      "argument": [
        "NSE_053",
        "0"
      ],
      "name": "",
      "msgidx": -1,
      "voice": "",
      "vid": "",
      "value": "",
      "said": ""
    },
    {
      "function": "XWTM",
      "argument": [
        "0.066"
      ],
      "name": "",
      "msgidx": -1,
      "voice": "",
      "vid": "",
      "value": "",
      "said": ""
    },
    {
      "function": "XWXB",
      "argument": [],
      "name": "",
      "msgidx": -1,
      "voice": "",
      "vid": "",
      "value": "",
      "said": ""
    },
    {
      "function": "XLCYDRAW",
      "argument": [
        "XLCYFIND,FindType.SP_C",
        "XLCYLOAD,Lucy.Type.BUST,BU_RIN_CMM5_0_SML",
        "XLCYLOAD,Lucy.Type.SP_L,SP_OFF",
        "XLCYLOAD,Lucy.Type.SP_R,SP_OFF",
        "XLCYLOAD,Lucy.Type.SP_C,SP_OFF",
        "XLCYFADE,0,0.25"
      ],
      "name": "",
      "msgidx": -1,
      "voice": "",
      "vid": "",
      "value": "",
      "said": ""
    },
    {
      "function": "XMESS",
      "argument": [
        "Nah, selesai."
      ],
      "name": "Shima Rin",
      "msgidx": 11,
      "voice": "RIN_2310_0012",
      "vid": "VID_RIN",
      "value": "",
      "said": ""
    },
    {
      "function": "XWCR",
      "argument": [],
      "name": "",
      "msgidx": -1,
      "voice": "",
      "vid": "",
      "value": "",
      "said": ""
    },
    {
      "function": "XLCYDRAW",
      "argument": [
        "XLCYFIND,FindType.SP_L|FindType.SP_R",
        "XLCYLOAD,Lucy.Type.BUST,BU_OFF",
        "XLCYLOAD,Lucy.Type.SP_L,SP_RIN_CMM5_0_SML",
        "XLCYLOAD,Lucy.Type.SP_R,SP_ENA_CMM4_0_LAU",
        "XLCYLOAD,Lucy.Type.SP_C,SP_OFF",
        "XLCYFADE,0,0.25"
      ],
      "name": "",
      "msgidx": -1,
      "voice": "",
      "vid": "",
      "value": "",
      "said": ""
    },
    {
      "function": "XMESS",
      "argument": [
        "Ooh, beneran gampang ya."
      ],
      "name": "Saitō Ena",
      "msgidx": 12,
      "voice": "ENA_0674_0013",
      "vid": "VID_ENA",
      "value": "",
      "said": ""
    },
    {
      "function": "XWCR",
      "argument": [],
      "name": "",
      "msgidx": -1,
      "voice": "",
      "vid": "",
      "value": "",
      "said": ""
    },
    {
      "function": "XLCYDRAW",
      "argument": [
        "XLCYLOAD,Lucy.Type.BUST,BU_OFF",
        "XLCYLOAD,Lucy.Type.AUTO,SP_RIN_CMM5_0_NML",
        "XLCYFADE,0,0.25"
      ],
      "name": "",
      "msgidx": -1,
      "voice": "",
      "vid": "",
      "value": "",
      "said": ""
    },
    {
      "function": "XMESS",
      "argument": [
        "Aku akan memanggangnya terus,",
        "jadi yang mau makan,",
        "makan saja duluan ya."
      ],
      "name": "Shima Rin",
      "msgidx": 13,
      "voice": "RIN_2311_0014",
      "vid": "VID_RIN",
      "value": "",
      "said": ""
    },
    {
      "function": "XWCR",
      "argument": [],
      "name": "",
      "msgidx": -1,
      "voice": "",
      "vid": "",
      "value": "",
      "said": ""
    },
    {
      "function": "XLCYDRAW",
      "argument": [
        "XLCYFIND,FindType.SP_L|FindType.SP_R",
        "XLCYLOAD,Lucy.Type.BUST,BU_OFF",
        "XLCYLOAD,Lucy.Type.SP_R,SP_NAD_CMB1_0_SER",
        "XLCYLOAD,Lucy.Type.SP_C,SP_OFF",
        "XLCYFADE,0,0.25"
      ],
      "name": "",
      "msgidx": -1,
      "voice": "",
      "vid": "",
      "value": "",
      "said": ""
    },
    {
      "function": "XMESS",
      "argument": [
        "Shap!"
      ],
      "name": "Kagamihara Nadeshiko",
      "msgidx": 14,
      "voice": "NAD_2733_0015",
      "vid": "VID_NAD",
      "value": "",
      "said": ""
    },
    {
      "function": "XWCR",
      "argument": [],
      "name": "",
      "msgidx": -1,
      "voice": "",
      "vid": "",
      "value": "",
      "said": ""
    },
    {
      "function": "XLCYDRAW",
      "argument": [
        "XLCYFIND,FindType.SP_C",
        "XLCYLOAD,Lucy.Type.BUST,BU_OFF",
        "XLCYLOAD,Lucy.Type.SP_L,SP_OFF",
        "XLCYLOAD,Lucy.Type.SP_R,SP_OFF",
        "XLCYLOAD,Lucy.Type.SP_C,SP_ENA_CMM4_0_SML",
        "XLCYFADE,0,0.25"
      ],
      "name": "",
      "msgidx": -1,
      "voice": "",
      "vid": "",
      "value": "",
      "said": ""
    },
    {
      "function": "XMESS",
      "argument": [
        "Oh iya, bikin teh ah."
      ],
      "name": "Saitō Ena",
      "msgidx": 15,
      "voice": "ENA_0675_0016",
      "vid": "VID_ENA",
      "value": "",
      "said": ""
    },
    {
      "function": "XWCR",
      "argument": [],
      "name": "",
      "msgidx": -1,
      "voice": "",
      "vid": "",
      "value": "",
      "said": ""
    },
    {
      "function": "XLCYDRAW",
      "argument": [
        "XLCYLOAD,Lucy.Type.BUST,BU_OFF",
        "XLCYLOAD,Lucy.Type.AUTO,SP_NAD_CMB1_0_LAU",
        "XLCYFADE,0,0.25"
      ],
      "name": "",
      "msgidx": -1,
      "voice": "",
      "vid": "",
      "value": "",
      "said": ""
    },
    {
      "function": "XMESS",
      "argument": [
        "Kalau begitu, aku rebus airnya yaa."
      ],
      "name": "Kagamihara Nadeshiko",
      "msgidx": 16,
      "voice": "NAD_2734_0017",
      "vid": "VID_NAD",
      "value": "",
      "said": ""
    },
    {
      "function": "XWCR",
      "argument": [],
      "name": "",
      "msgidx": -1,
      "voice": "",
      "vid": "",
      "value": "",
      "said": ""
    },
    {
      "function": "XFADE",
      "argument": [
        "XFTS,MaskTexture.None,0",
        "XFOT,0.5"
      ],
      "name": "",
      "msgidx": -1,
      "voice": "",
      "vid": "",
      "value": "",
      "said": ""
    },
    {
      "function": "XWXB",
      "argument": [],
      "name": "",
      "msgidx": -1,
      "voice": "",
      "vid": "",
      "value": "",
      "said": ""
    },
    {
      "function": "SNSE",
      "argument": [
        "NSE_OFF",
        "0"
      ],
      "name": "",
      "msgidx": -1,
      "voice": "",
      "vid": "",
      "value": "",
      "said": ""
    },
    {
      "function": "XWXB",
      "argument": [],
      "name": "",
      "msgidx": -1,
      "voice": "",
      "vid": "",
      "value": "",
      "said": ""
    },
    {
      "function": "XLCYDRAW",
      "argument": [
        "XLCYLOAD,Lucy.Type.BACK,BG_189_C0",
        "XLCYFADE,0,0.001"
      ],
      "name": "",
      "msgidx": -1,
      "voice": "",
      "vid": "",
      "value": "",
      "said": ""
    },
    {
      "function": "XLCYDRAW",
      "argument": [
        "XLCYINIT",
        "XLCYFIND,FindType.SP_C",
        "XLCYLOAD,Lucy.Type.BUST,BU_OFF",
        "XLCYLOAD,Lucy.Type.SP_L,SP_OFF",
        "XLCYLOAD,Lucy.Type.SP_R,SP_OFF",
        "XLCYLOAD,Lucy.Type.SP_C,SP_OFF",
        "XLCYLOAD,Lucy.Type.MG_0,MG_OFF",
        "XLCYLOAD,Lucy.Type.MG_1,MG_OFF",
        "XLCYFADE,0,0.25"
      ],
      "name": "",
      "msgidx": -1,
      "voice": "",
      "vid": "",
      "value": "",
      "said": ""
    },
    {
      "function": "SBGM",
      "argument": [
        "BGM_10"
      ],
      "name": "",
      "msgidx": -1,
      "voice": "",
      "vid": "",
      "value": "",
      "said": ""
    },
    {
      "function": "SESE",
      "argument": [
        "ESE_OFF",
        "0"
      ],
      "name": "",
      "msgidx": -1,
      "voice": "",
      "vid": "",
      "value": "",
      "said": ""
    },
    {
      "function": "XMON",
      "argument": [],
      "name": "",
      "msgidx": -1,
      "voice": "",
      "vid": "",
      "value": "",
      "said": ""
    },
    {
      "function": "XFADE",
      "argument": [
        "XFTS,MaskTexture.None,0",
        "XFIN,0.5"
      ],
      "name": "",
      "msgidx": -1,
      "voice": "",
      "vid": "",
      "value": "",
      "said": ""
    },
    {
      "function": "XMESS",
      "argument": [
        "Tu, wa..."
      ],
      "name": "Kagamihara Nadeshiko",
      "msgidx": 17,
      "voice": "NAD_2735_0018",
      "vid": "VID_NAD",
      "value": "",
      "said": ""
    },
    {
      "function": "XWCR",
      "argument": [],
      "name": "",
      "msgidx": -1,
      "voice": "",
      "vid": "",
      "value": "",
      "said": ""
    },
    {
      "function": "XMESS",
      "argument": [
        "Selamat maka─n."
      ],
      "name": "Semuanya（Rin, Nadeshiko, Ena）",
      "msgidx": 18,
      "voice": "RIN_2312_0019",
      "vid": "VID_RIN",
      "value": "",
      "said": ""
    },
    {
      "function": "XWCR",
      "argument": [],
      "name": "",
      "msgidx": -1,
      "voice": "",
      "vid": "",
      "value": "",
      "said": ""
    },
    {
      "function": "XFADE",
      "argument": [
        "XFTS,MaskTexture.None,0",
        "XFOT,0.5"
      ],
      "name": "",
      "msgidx": -1,
      "voice": "",
      "vid": "",
      "value": "",
      "said": ""
    },
    {
      "function": "XWXB",
      "argument": [],
      "name": "",
      "msgidx": -1,
      "voice": "",
      "vid": "",
      "value": "",
      "said": ""
    },
    {
      "function": "SNSE",
      "argument": [
        "NSE_OFF",
        "0"
      ],
      "name": "",
      "msgidx": -1,
      "voice": "",
      "vid": "",
      "value": "",
      "said": ""
    },
    {
      "function": "XWXB",
      "argument": [],
      "name": "",
      "msgidx": -1,
      "voice": "",
      "vid": "",
      "value": "",
      "said": ""
    },
    {
      "function": "XLCYDRAW",
      "argument": [
        "XLCYLOAD,Lucy.Type.BACK,BG_124_C0",
        "XLCYFADE,0,0.001"
      ],
      "name": "",
      "msgidx": -1,
      "voice": "",
      "vid": "",
      "value": "",
      "said": ""
    },
    {
      "function": "XLCYDRAW",
      "argument": [
        "XLCYFIND,FindType.SP_L|FindType.SP_R",
        "XLCYLOAD,Lucy.Type.BUST,BU_OFF",
        "XLCYLOAD,Lucy.Type.SP_L,SP_RIN_CMM5_0_NML",
        "XLCYLOAD,Lucy.Type.SP_R,SP_NAD_CMB1_0_SML",
        "XLCYLOAD,Lucy.Type.SP_C,SP_OFF",
        "XLCYFADE,0,0.25"
      ],
      "name": "",
      "msgidx": -1,
      "voice": "",
      "vid": "",
      "value": "",
      "said": ""
    },
    {
      "function": "SBGM",
      "argument": [
        "BGM_SAME"
      ],
      "name": "",
      "msgidx": -1,
      "voice": "",
      "vid": "",
      "value": "",
      "said": ""
    },
    {
      "function": "SESE",
      "argument": [
        "ESE_OFF",
        "0"
      ],
      "name": "",
      "msgidx": -1,
      "voice": "",
      "vid": "",
      "value": "",
      "said": ""
    },
    {
      "function": "XMON",
      "argument": [],
      "name": "",
      "msgidx": -1,
      "voice": "",
      "vid": "",
      "value": "",
      "said": ""
    },
    {
      "function": "XFADE",
      "argument": [
        "XFTS,MaskTexture.None,0",
        "XFIN,0.5"
      ],
      "name": "",
      "msgidx": -1,
      "voice": "",
      "vid": "",
      "value": "",
      "said": ""
    },
    {
      "function": "XMESS",
      "argument": [
        "Butaman panggang dan",
        "Anman panggang hangatnya",
        "banyak banget ya."
      ],
      "name": "Kagamihara Nadeshiko",
      "msgidx": 19,
      "voice": "NAD_2737_0020",
      "vid": "VID_NAD",
      "value": "",
      "said": ""
    },
    {
      "function": "XWCR",
      "argument": [],
      "name": "",
      "msgidx": -1,
      "voice": "",
      "vid": "",
      "value": "",
      "said": ""
    },
    {
      "function": "XLCYDRAW",
      "argument": [
        "XLCYLOAD,Lucy.Type.BUST,BU_OFF",
        "XLCYLOAD,Lucy.Type.AUTO,SP_RIN_CMM5_0_CON",
        "XLCYFADE,0,0.25"
      ],
      "name": "",
      "msgidx": -1,
      "voice": "",
      "vid": "",
      "value": "",
      "said": ""
    },
    {
      "function": "XMESS",
      "argument": [
        "Apa terlalu banyak ya?"
      ],
      "name": "Shima Rin",
      "msgidx": 20,
      "voice": "RIN_2313_0021",
      "vid": "VID_RIN",
      "value": "",
      "said": ""
    },
    {
      "function": "XWCR",
      "argument": [],
      "name": "",
      "msgidx": -1,
      "voice": "",
      "vid": "",
      "value": "",
      "said": ""
    },
    {
      "function": "XLCYDRAW",
      "argument": [
        "XLCYFIND,FindType.SP_L|FindType.SP_R",
        "XLCYLOAD,Lucy.Type.BUST,BU_OFF",
        "XLCYLOAD,Lucy.Type.SP_R,SP_ENA_CMM4_0_SML",
        "XLCYLOAD,Lucy.Type.SP_C,SP_OFF",
        "XLCYFADE,0,0.25"
      ],
      "name": "",
      "msgidx": -1,
      "voice": "",
      "vid": "",
      "value": "",
      "said": ""
    },
    {
      "function": "XMESS",
      "argument": [
        "Singkirkan kekhawatiranmu itu,",
        "dan mari santap sebelum dingin."
      ],
      "name": "Saitō Ena",
      "msgidx": 21,
      "voice": "ENA_0677_0022",
      "vid": "VID_ENA",
      "value": "",
      "said": ""
    },
    {
      "function": "XWCR",
      "argument": [],
      "name": "",
      "msgidx": -1,
      "voice": "",
      "vid": "",
      "value": "",
      "said": ""
    },
    {
      "function": "XLCYDRAW",
      "argument": [
        "XLCYFIND,FindType.SP_C",
        "XLCYLOAD,Lucy.Type.BUST,BU_NAD_CMB1_1_SML",
        "XLCYLOAD,Lucy.Type.SP_L,SP_OFF",
        "XLCYLOAD,Lucy.Type.SP_R,SP_OFF",
        "XLCYLOAD,Lucy.Type.SP_C,SP_OFF",
        "XLCYFADE,0,0.25"
      ],
      "name": "",
      "msgidx": -1,
      "voice": "",
      "vid": "",
      "value": "",
      "said": ""
    },
    {
      "function": "XMESS",
      "argument": [
        "Baiklah, dimulai dari bakpao dagingnya.",
        "Tambahkan sedikit tare untuk Gyoza..."
      ],
      "name": "Kagamihara Nadeshiko",
      "msgidx": 22,
      "voice": "NAD_2738_0023",
      "vid": "VID_NAD",
      "value": "",
      "said": ""
    },
    {
      "function": "XWCR",
      "argument": [],
      "name": "",
      "msgidx": -1,
      "voice": "",
      "vid": "",
      "value": "",
      "said": ""
    },
    {
      "function": "XLCYDRAW",
      "argument": [
        "XLCYFIND,FindType.SP_C",
        "XLCYLOAD,Lucy.Type.BUST,BU_NAD_CMB1_0_SUP",
        "XLCYLOAD,Lucy.Type.SP_L,SP_OFF",
        "XLCYLOAD,Lucy.Type.SP_R,SP_OFF",
        "XLCYLOAD,Lucy.Type.SP_C,SP_OFF",
        "XLCYFADE,0,0.25"
      ],
      "name": "",
      "msgidx": -1,
      "voice": "",
      "vid": "",
      "value": "",
      "said": ""
    },
    {
      "function": "XMESS",
      "argument": [
        "Aーm.... Mm?!"
      ],
      "name": "Kagamihara Nadeshiko",
      "msgidx": 23,
      "voice": "NAD_2739_0024",
      "vid": "VID_NAD",
      "value": "",
      "said": ""
    },
    {
      "function": "XWCR",
      "argument": [],
      "name": "",
      "msgidx": -1,
      "voice": "",
      "vid": "",
      "value": "",
      "said": ""
    },
    {
      "function": "XLCYDRAW",
      "argument": [
        "XLCYFIND,FindType.SP_C",
        "XLCYLOAD,Lucy.Type.BUST,BU_NAD_CMB1_0_LAU",
        "XLCYLOAD,Lucy.Type.SP_L,SP_OFF",
        "XLCYLOAD,Lucy.Type.SP_R,SP_OFF",
        "XLCYLOAD,Lucy.Type.SP_C,SP_OFF",
        "XLCYFADE,0,0.25"
      ],
      "name": "",
      "msgidx": -1,
      "voice": "",
      "vid": "",
      "value": "",
      "said": ""
    },
    {
      "function": "XMESS",
      "argument": [
        "Rin-chan,",
        "ini sangat krispi dan enak loh!"
      ],
      "name": "Kagamihara Nadeshiko",
      "msgidx": 24,
      "voice": "NAD_2740_0025",
      "vid": "VID_NAD",
      "value": "",
      "said": ""
    },
    {
      "function": "XWCR",
      "argument": [],
      "name": "",
      "msgidx": -1,
      "voice": "",
      "vid": "",
      "value": "",
      "said": ""
    },
    {
      "function": "XLCYDRAW",
      "argument": [
        "XLCYFIND,FindType.SP_C",
        "XLCYLOAD,Lucy.Type.BUST,BU_RIN_CMM5_0_SML",
        "XLCYLOAD,Lucy.Type.SP_L,SP_OFF",
        "XLCYLOAD,Lucy.Type.SP_R,SP_OFF",
        "XLCYLOAD,Lucy.Type.SP_C,SP_OFF",
        "XLCYFADE,0,0.25"
      ],
      "name": "",
      "msgidx": -1,
      "voice": "",
      "vid": "",
      "value": "",
      "said": ""
    },
    {
      "function": "XMESS",
      "argument": [
        "Berkat mentega,",
        "luarnya jadi garing ya."
      ],
      "name": "Shima Rin",
      "msgidx": 25,
      "voice": "RIN_2314_0026",
      "vid": "VID_RIN",
      "value": "",
      "said": ""
    },
    {
      "function": "XWCR",
      "argument": [],
      "name": "",
      "msgidx": -1,
      "voice": "",
      "vid": "",
      "value": "",
      "said": ""
    },
    {
      "function": "XLCYDRAW",
      "argument": [
        "XLCYFIND,FindType.SP_C",
        "XLCYLOAD,Lucy.Type.BUST,BU_ENA_CMM4_0_SUP",
        "XLCYLOAD,Lucy.Type.SP_L,SP_OFF",
        "XLCYLOAD,Lucy.Type.SP_R,SP_OFF",
        "XLCYLOAD,Lucy.Type.SP_C,SP_OFF",
        "XLCYFADE,0,0.25"
      ],
      "name": "",
      "msgidx": -1,
      "voice": "",
      "vid": "",
      "value": "",
      "said": ""
    },
    {
      "function": "XMESS",
      "argument": [
        "Hanya dengan ditekan memakai",
        "Hot Sand, bisa sangat",
        "berubah begini toh?!"
      ],
      "name": "Saitō Ena",
      "msgidx": 26,
      "voice": "ENA_0678_0027",
      "vid": "VID_ENA",
      "value": "",
      "said": ""
    },
    {
      "function": "XWCR",
      "argument": [],
      "name": "",
      "msgidx": -1,
      "voice": "",
      "vid": "",
      "value": "",
      "said": ""
    },
    {
      "function": "XLCYDRAW",
      "argument": [
        "XLCYFIND,FindType.SP_L|FindType.SP_R",
        "XLCYLOAD,Lucy.Type.BUST,BU_OFF",
        "XLCYLOAD,Lucy.Type.SP_L,SP_RIN_CMM5_0_CON",
        "XLCYLOAD,Lucy.Type.SP_R,SP_NAD_CMB1_0_SML",
        "XLCYLOAD,Lucy.Type.SP_C,SP_OFF",
        "XLCYFADE,0,0.25"
      ],
      "name": "",
      "msgidx": -1,
      "voice": "",
      "vid": "",
      "value": "",
      "said": ""
    },
    {
      "function": "XMESS",
      "argument": [
        "Meski begitu, ini enak banget...",
        "Aku seharusnya membeli lebih banyak."
      ],
      "name": "Shima Rin",
      "msgidx": 27,
      "voice": "RIN_2315_0028",
      "vid": "VID_RIN",
      "value": "",
      "said": ""
    },
    {
      "function": "XWCR",
      "argument": [],
      "name": "",
      "msgidx": -1,
      "voice": "",
      "vid": "",
      "value": "",
      "said": ""
    },
    {
      "function": "XLCYDRAW",
      "argument": [
        "XLCYLOAD,Lucy.Type.BUST,BU_OFF",
        "XLCYLOAD,Lucy.Type.AUTO,SP_NAD_CMB1_0_SML",
        "XLCYFADE,0,0.25"
      ],
      "name": "",
      "msgidx": -1,
      "voice": "",
      "vid": "",
      "value": "",
      "said": ""
    },
    {
      "function": "XMESS",
      "argument": [
        "Mm, Anman panggang juga boleh ya."
      ],
      "name": "Kagamihara Nadeshiko",
      "msgidx": 28,
      "voice": "NAD_2741_0029",
      "vid": "VID_NAD",
      "value": "",
      "said": ""
    },
    {
      "function": "XWCR",
      "argument": [],
      "name": "",
      "msgidx": -1,
      "voice": "",
      "vid": "",
      "value": "",
      "said": ""
    },
    {
      "function": "XLCYDRAW",
      "argument": [
        "XLCYFIND,FindType.SP_L|FindType.SP_R",
        "XLCYLOAD,Lucy.Type.BUST,BU_OFF",
        "XLCYLOAD,Lucy.Type.SP_R,SP_ENA_CMM4_0_SML",
        "XLCYLOAD,Lucy.Type.SP_C,SP_OFF",
        "XLCYFADE,0,0.25"
      ],
      "name": "",
      "msgidx": -1,
      "voice": "",
      "vid": "",
      "value": "",
      "said": ""
    },
    {
      "function": "XMESS",
      "argument": [
        "Apa ada yang bisa dibuat begini",
        "selain Butaman dan Anman ya?"
      ],
      "name": "Saitō Ena",
      "msgidx": 29,
      "voice": "ENA_0679_0030",
      "vid": "VID_ENA",
      "value": "",
      "said": ""
    },
    {
      "function": "XWCR",
      "argument": [],
      "name": "",
      "msgidx": -1,
      "voice": "",
      "vid": "",
      "value": "",
      "said": ""
    },
    {
      "function": "XLCYDRAW",
      "argument": [
        "XLCYLOAD,Lucy.Type.BUST,BU_OFF",
        "XLCYLOAD,Lucy.Type.AUTO,SP_RIN_CMM5_0_NML",
        "XLCYFADE,0,0.25"
      ],
      "name": "",
      "msgidx": -1,
      "voice": "",
      "vid": "",
      "value": "",
      "said": ""
    },
    {
      "function": "XMESS",
      "argument": [
        "Mungkin bisa pakai roti biasa.",
        "Kayak Melonpan atau Roti keju kukus."
      ],
      "name": "Shima Rin",
      "msgidx": 30,
      "voice": "RIN_2316_0031",
      "vid": "VID_RIN",
      "value": "",
      "said": ""
    },
    {
      "function": "XWCR",
      "argument": [],
      "name": "",
      "msgidx": -1,
      "voice": "",
      "vid": "",
      "value": "",
      "said": ""
    },
    {
      "function": "XLCYDRAW",
      "argument": [
        "XLCYFIND,FindType.SP_L|FindType.SP_R",
        "XLCYLOAD,Lucy.Type.BUST,BU_OFF",
        "XLCYLOAD,Lucy.Type.SP_R,SP_NAD_CMB1_0_LAU",
        "XLCYLOAD,Lucy.Type.SP_C,SP_OFF",
        "XLCYFADE,0,0.25"
      ],
      "name": "",
      "msgidx": -1,
      "voice": "",
      "vid": "",
      "value": "",
      "said": ""
    },
    {
      "function": "XMESS",
      "argument": [
        "Itu boleh juga!",
        "Melonpan yang diolesi mentega dan",
        "dipanggang pasti enak!"
      ],
      "name": "Kagamihara Nadeshiko",
      "msgidx": 31,
      "voice": "NAD_2742_0032",
      "vid": "VID_NAD",
      "value": "",
      "said": ""
    },
    {
      "function": "XWCR",
      "argument": [],
      "name": "",
      "msgidx": -1,
      "voice": "",
      "vid": "",
      "value": "",
      "said": ""
    },
    {
      "function": "XLCYDRAW",
      "argument": [
        "XLCYLOAD,Lucy.Type.BUST,BU_OFF",
        "XLCYLOAD,Lucy.Type.AUTO,SP_NAD_CMB1_0_SML",
        "XLCYFADE,0,0.25"
      ],
      "name": "",
      "msgidx": -1,
      "voice": "",
      "vid": "",
      "value": "",
      "said": ""
    },
    {
      "function": "XMESS",
      "argument": [
        "Dengan hasil begini,",
        "Hot Sand Maker itu hebat ya."
      ],
      "name": "Kagamihara Nadeshiko",
      "msgidx": 32,
      "voice": "NAD_2743_0033",
      "vid": "VID_NAD",
      "value": "",
      "said": ""
    },
    {
      "function": "XWCR",
      "argument": [],
      "name": "",
      "msgidx": -1,
      "voice": "",
      "vid": "",
      "value": "",
      "said": ""
    },
    {
      "function": "XLCYDRAW",
      "argument": [
        "XLCYLOAD,Lucy.Type.BUST,BU_OFF",
        "XLCYLOAD,Lucy.Type.AUTO,SP_RIN_CMM5_0_SML",
        "XLCYFADE,0,0.25"
      ],
      "name": "",
      "msgidx": -1,
      "voice": "",
      "vid": "",
      "value": "",
      "said": ""
    },
    {
      "function": "XMESS",
      "argument": [
        "Iya."
      ],
      "name": "Shima Rin",
      "msgidx": 33,
      "voice": "RIN_2317_0034",
      "vid": "VID_RIN",
      "value": "",
      "said": ""
    },
    {
      "function": "XWCR",
      "argument": [],
      "name": "",
      "msgidx": -1,
      "voice": "",
      "vid": "",
      "value": "",
      "said": ""
    },
    {
      "function": "XFADE",
      "argument": [
        "XFTS,MaskTexture.None,0",
        "XFOT,0.5"
      ],
      "name": "",
      "msgidx": -1,
      "voice": "",
      "vid": "",
      "value": "",
      "said": ""
    },
    {
      "function": "XWXB",
      "argument": [],
      "name": "",
      "msgidx": -1,
      "voice": "",
      "vid": "",
      "value": "",
      "said": ""
    },
    {
      "function": "SNSE",
      "argument": [
        "NSE_OFF",
        "0"
      ],
      "name": "",
      "msgidx": -1,
      "voice": "",
      "vid": "",
      "value": "",
      "said": ""
    },
    {
      "function": "XWXB",
      "argument": [],
      "name": "",
      "msgidx": -1,
      "voice": "",
      "vid": "",
      "value": "",
      "said": ""
    },
    {
      "function": "XLCYDRAW",
      "argument": [
        "XLCYLOAD,Lucy.Type.BACK,BG_189_C0",
        "XLCYFADE,0,0.001"
      ],
      "name": "",
      "msgidx": -1,
      "voice": "",
      "vid": "",
      "value": "",
      "said": ""
    },
    {
      "function": "XLCYDRAW",
      "argument": [
        "XLCYINIT",
        "XLCYFIND,FindType.SP_C",
        "XLCYLOAD,Lucy.Type.BUST,BU_OFF",
        "XLCYLOAD,Lucy.Type.SP_L,SP_OFF",
        "XLCYLOAD,Lucy.Type.SP_R,SP_OFF",
        "XLCYLOAD,Lucy.Type.SP_C,SP_OFF",
        "XLCYLOAD,Lucy.Type.MG_0,MG_OFF",
        "XLCYLOAD,Lucy.Type.MG_1,MG_OFF",
        "XLCYFADE,0,0.25"
      ],
      "name": "",
      "msgidx": -1,
      "voice": "",
      "vid": "",
      "value": "",
      "said": ""
    },
    {
      "function": "SBGM",
      "argument": [
        "BGM_SAME"
      ],
      "name": "",
      "msgidx": -1,
      "voice": "",
      "vid": "",
      "value": "",
      "said": ""
    },
    {
      "function": "SESE",
      "argument": [
        "ESE_OFF",
        "0"
      ],
      "name": "",
      "msgidx": -1,
      "voice": "",
      "vid": "",
      "value": "",
      "said": ""
    },
    {
      "function": "XMON",
      "argument": [],
      "name": "",
      "msgidx": -1,
      "voice": "",
      "vid": "",
      "value": "",
      "said": ""
    },
    {
      "function": "XFADE",
      "argument": [
        "XFTS,MaskTexture.None,0",
        "XFIN,0.5"
      ],
      "name": "",
      "msgidx": -1,
      "voice": "",
      "vid": "",
      "value": "",
      "said": ""
    },
    {
      "function": "XMESS",
      "argument": [
        "Terimakasih atas makanannyaa."
      ],
      "name": "Kagamihara Nadeshiko",
      "msgidx": 34,
      "voice": "NAD_2744_0035",
      "vid": "VID_NAD",
      "value": "",
      "said": ""
    },
    {
      "function": "XWCR",
      "argument": [],
      "name": "",
      "msgidx": -1,
      "voice": "",
      "vid": "",
      "value": "",
      "said": ""
    },
    {
      "function": "XMESS",
      "argument": [
        "Kau puas?"
      ],
      "name": "Shima Rin",
      "msgidx": 35,
      "voice": "RIN_2318_0036",
      "vid": "VID_RIN",
      "value": "",
      "said": ""
    },
    {
      "function": "XWCR",
      "argument": [],
      "name": "",
      "msgidx": -1,
      "voice": "",
      "vid": "",
      "value": "",
      "said": ""
    },
    {
      "function": "XMESS",
      "argument": [
        "Sangat puas!",
        "Hawa dingin pun sampai terhempas."
      ],
      "name": "Kagamihara Nadeshiko",
      "msgidx": 36,
      "voice": "NAD_2745_0037",
      "vid": "VID_NAD",
      "value": "",
      "said": ""
    },
    {
      "function": "XWCR",
      "argument": [],
      "name": "",
      "msgidx": -1,
      "voice": "",
      "vid": "",
      "value": "",
      "said": ""
    },
    {
      "function": "XMESS",
      "argument": [
        "Syukur deh kalau begitu.",
        "Nanti mari kita buat lagi",
        "dan makan bersama ya."
      ],
      "name": "Shima Rin",
      "msgidx": 37,
      "voice": "RIN_2319_0038",
      "vid": "VID_RIN",
      "value": "",
      "said": ""
    },
    {
      "function": "XWCR",
      "argument": [],
      "name": "",
      "msgidx": -1,
      "voice": "",
      "vid": "",
      "value": "",
      "said": ""
    },
    {
      "function": "XMESS",
      "argument": [
        "Iya!"
      ],
      "name": "Kagamihara Nadeshiko",
      "msgidx": 38,
      "voice": "NAD_2746_0039",
      "vid": "VID_NAD",
      "value": "",
      "said": ""
    },
    {
      "function": "XWAI",
      "argument": [],
      "name": "",
      "msgidx": -1,
      "voice": "",
      "vid": "",
      "value": "",
      "said": ""
    },
    {
      "function": "XFADE",
      "argument": [
        "XFED,0.5"
      ],
      "name": "",
      "msgidx": -1,
      "voice": "",
      "vid": "",
      "value": "",
      "said": ""
    },
    {
      "function": "XCLR",
      "argument": [],
      "name": "",
      "msgidx": -1,
      "voice": "",
      "vid": "",
      "value": "",
      "said": ""
    },
    {
      "function": "XEOS",
      "argument": [],
      "name": "",
      "msgidx": -1,
      "voice": "",
      "vid": "",
      "value": "",
      "said": ""
    }
  ]
}