{
  "bgm": [
    "BGM_04",
    "BGM_06"
  ],
  "bgp": [
    "BG_048_A0",
    "BG_095_A0",
    "BG_156_A0",
    "BG_189_A0",
    "BG_192_A0",
    "BG_BLACK"
  ],
  "egp": [],
  "cid": [
    "AOI",
    "CHI",
    "MIN",
    "NAD",
    "RIN"
  ],
  "label": [
    {
      "name": "SCR_L_YC_YA_0_04_START",
      "line": 0
    }
  ],
  "message": [
    {
      "function": "XAUTOSAVE_SCENE",
      "argument": [],
      "name": "",
      "msgidx": -1,
      "voice": "",
      "vid": "",
      "value": "",
      "said": ""
    },
    {
      "function": "XCLR",
      "argument": [],
      "name": "",
      "msgidx": -1,
      "voice": "",
      "vid": "",
      "value": "",
      "said": ""
    },
    {
      "function": "XFADE",
      "argument": [
        "XFTS,MaskTexture.None,0",
        "XFOT,0.5"
      ],
      "name": "",
      "msgidx": -1,
      "voice": "",
      "vid": "",
      "value": "",
      "said": ""
    },
    {
      "function": "XWXB",
      "argument": [],
      "name": "",
      "msgidx": -1,
      "voice": "",
      "vid": "",
      "value": "",
      "said": ""
    },
    {
      "function": "SNSE",
      "argument": [
        "NSE_OFF",
        "0"
      ],
      "name": "",
      "msgidx": -1,
      "voice": "",
      "vid": "",
      "value": "",
      "said": ""
    },
    {
      "function": "XWXB",
      "argument": [],
      "name": "",
      "msgidx": -1,
      "voice": "",
      "vid": "",
      "value": "",
      "said": ""
    },
    {
      "function": "XLCYDRAW",
      "argument": [
        "XLCYLOAD,Lucy.Type.BACK,BG_BLACK",
        "XLCYFADE,0,0.001"
      ],
      "name": "",
      "msgidx": -1,
      "voice": "",
      "vid": "",
      "value": "",
      "said": ""
    },
    {
      "function": "XLCYDRAW",
      "argument": [
        "XLCYINIT",
        "XLCYFIND,FindType.SP_C",
        "XLCYLOAD,Lucy.Type.BUST,BU_OFF",
        "XLCYLOAD,Lucy.Type.SP_L,SP_OFF",
        "XLCYLOAD,Lucy.Type.SP_R,SP_OFF",
        "XLCYLOAD,Lucy.Type.SP_C,SP_OFF",
        "XLCYLOAD,Lucy.Type.MG_0,MG_OFF",
        "XLCYLOAD,Lucy.Type.MG_1,MG_OFF",
        "XLCYFADE,0,0.25"
      ],
      "name": "",
      "msgidx": -1,
      "voice": "",
      "vid": "",
      "value": "",
      "said": ""
    },
    {
      "function": "SBGM",
      "argument": [
        "BGM_OFF"
      ],
      "name": "",
      "msgidx": -1,
      "voice": "",
      "vid": "",
      "value": "",
      "said": ""
    },
    {
      "function": "SESE",
      "argument": [
        "ESE_OFF",
        "0"
      ],
      "name": "",
      "msgidx": -1,
      "voice": "",
      "vid": "",
      "value": "",
      "said": ""
    },
    {
      "function": "XMOF",
      "argument": [],
      "name": "",
      "msgidx": -1,
      "voice": "",
      "vid": "",
      "value": "",
      "said": ""
    },
    {
      "function": "XFADE",
      "argument": [
        "XFTS,MaskTexture.None,0",
        "XFIN,0.5"
      ],
      "name": "",
      "msgidx": -1,
      "voice": "",
      "vid": "",
      "value": "",
      "said": ""
    },
    {
      "function": "XLOGOIN",
      "argument": [],
      "name": "",
      "msgidx": -1,
      "voice": "",
      "vid": "",
      "value": "",
      "said": ""
    },
    {
      "function": "XLCYDRAW",
      "argument": [
        "XLCYLOAD,Lucy.Type.BACK,BG_192_A0",
        "XLCYFADE,0,0.25"
      ],
      "name": "",
      "msgidx": -1,
      "voice": "",
      "vid": "",
      "value": "",
      "said": ""
    },
    {
      "function": "XLOGOOUT",
      "argument": [],
      "name": "",
      "msgidx": -1,
      "voice": "",
      "vid": "",
      "value": "",
      "said": ""
    },
    {
      "function": "XMOF",
      "argument": [],
      "name": "",
      "msgidx": -1,
      "voice": "",
      "vid": "",
      "value": "",
      "said": ""
    },
    {
      "function": "XCLR",
      "argument": [],
      "name": "",
      "msgidx": -1,
      "voice": "",
      "vid": "",
      "value": "",
      "said": ""
    },
    {
      "function": "XCMNT",
      "argument": [
        "『Sedang mampir di dek observasi tepi danau』"
      ],
      "name": "",
      "msgidx": -1,
      "voice": "",
      "vid": "",
      "value": "",
      "said": ""
    },
    {
      "function": "XFADE",
      "argument": [
        "XFTS,MaskTexture.None,0",
        "XFOT,0.5"
      ],
      "name": "",
      "msgidx": -1,
      "voice": "",
      "vid": "",
      "value": "",
      "said": ""
    },
    {
      "function": "XWXB",
      "argument": [],
      "name": "",
      "msgidx": -1,
      "voice": "",
      "vid": "",
      "value": "",
      "said": ""
    },
    {
      "function": "SNSE",
      "argument": [
        "NSE_OFF",
        "0"
      ],
      "name": "",
      "msgidx": -1,
      "voice": "",
      "vid": "",
      "value": "",
      "said": ""
    },
    {
      "function": "XWXB",
      "argument": [],
      "name": "",
      "msgidx": -1,
      "voice": "",
      "vid": "",
      "value": "",
      "said": ""
    },
    {
      "function": "XLCYDRAW",
      "argument": [
        "XLCYLOAD,Lucy.Type.BACK,BG_095_A0",
        "XLCYFADE,0,0.001"
      ],
      "name": "",
      "msgidx": -1,
      "voice": "",
      "vid": "",
      "value": "",
      "said": ""
    },
    {
      "function": "XLCYDRAW",
      "argument": [
        "XLCYFIND,FindType.SP_L|FindType.SP_R",
        "XLCYLOAD,Lucy.Type.BUST,BU_OFF",
        "XLCYLOAD,Lucy.Type.SP_L,SP_RIN_CMP1_0_SML",
        "XLCYLOAD,Lucy.Type.SP_R,SP_NAD_CMP_0_SML",
        "XLCYLOAD,Lucy.Type.SP_C,SP_OFF",
        "XLCYFADE,0,0.25"
      ],
      "name": "",
      "msgidx": -1,
      "voice": "",
      "vid": "",
      "value": "",
      "said": ""
    },
    {
      "function": "SBGM",
      "argument": [
        "BGM_04"
      ],
      "name": "",
      "msgidx": -1,
      "voice": "",
      "vid": "",
      "value": "",
      "said": ""
    },
    {
      "function": "SESE",
      "argument": [
        "ESE_OFF",
        "0"
      ],
      "name": "",
      "msgidx": -1,
      "voice": "",
      "vid": "",
      "value": "",
      "said": ""
    },
    {
      "function": "XMON",
      "argument": [],
      "name": "",
      "msgidx": -1,
      "voice": "",
      "vid": "",
      "value": "",
      "said": ""
    },
    {
      "function": "XFADE",
      "argument": [
        "XFTS,MaskTexture.None,0",
        "XFIN,0.5"
      ],
      "name": "",
      "msgidx": -1,
      "voice": "",
      "vid": "",
      "value": "",
      "said": ""
    },
    {
      "function": "XMESS",
      "argument": [
        "Baiklah, mari kita naik gunung",
        "dan pergi ke dek observasi."
      ],
      "name": "Shima Rin（Non-Voiced）",
      "msgidx": 0,
      "voice": "",
      "vid": "",
      "value": "",
      "said": ""
    },
    {
      "function": "XWCR",
      "argument": [],
      "name": "",
      "msgidx": -1,
      "voice": "",
      "vid": "",
      "value": "",
      "said": ""
    },
    {
      "function": "XLCYDRAW",
      "argument": [
        "XLCYLOAD,Lucy.Type.BUST,BU_OFF",
        "XLCYLOAD,Lucy.Type.AUTO,SP_NAD_CMP_0_LAU",
        "XLCYFADE,0,0.25"
      ],
      "name": "",
      "msgidx": -1,
      "voice": "",
      "vid": "",
      "value": "",
      "said": ""
    },
    {
      "function": "XMESS",
      "argument": [
        "Aku sudah beberapa kali kesini, tapi",
        "aku belum pernah ke dek observasi,",
        "jadi tidak sabar deh."
      ],
      "name": "Kagamihara Nadeshiko",
      "msgidx": 1,
      "voice": "NAD_0202_0001",
      "vid": "VID_NAD",
      "value": "",
      "said": ""
    },
    {
      "function": "XWCR",
      "argument": [],
      "name": "",
      "msgidx": -1,
      "voice": "",
      "vid": "",
      "value": "",
      "said": ""
    },
    {
      "function": "XLCYDRAW",
      "argument": [
        "XLCYFIND,FindType.SP_L|FindType.SP_R",
        "XLCYLOAD,Lucy.Type.BUST,BU_OFF",
        "XLCYLOAD,Lucy.Type.SP_L,SP_CHI_CMP_0_NML",
        "XLCYLOAD,Lucy.Type.SP_R,SP_AOI_CMP_0_CON",
        "XLCYLOAD,Lucy.Type.SP_C,SP_OFF",
        "XLCYFADE,0,0.25"
      ],
      "name": "",
      "msgidx": -1,
      "voice": "",
      "vid": "",
      "value": "",
      "said": ""
    },
    {
      "function": "XMESS",
      "argument": [
        "Meski begitu, Gunung Fuji hari ini",
        "memakai topi yaa."
      ],
      "name": "Inuyama Aoi",
      "msgidx": 2,
      "voice": "AOI_0139_0002",
      "vid": "VID_AOI",
      "value": "",
      "said": ""
    },
    {
      "function": "XWCR",
      "argument": [],
      "name": "",
      "msgidx": -1,
      "voice": "",
      "vid": "",
      "value": "",
      "said": ""
    },
    {
      "function": "XLCYDRAW",
      "argument": [
        "XLCYLOAD,Lucy.Type.BUST,BU_OFF",
        "XLCYLOAD,Lucy.Type.AUTO,SP_CHI_CMP_0_SML",
        "XLCYFADE,0,0.25"
      ],
      "name": "",
      "msgidx": -1,
      "voice": "",
      "vid": "",
      "value": "",
      "said": ""
    },
    {
      "function": "XMESS",
      "argument": [
        "Tunggu dulu. Cuaca di Gunung Fuji",
        "mudah berubah. Mungkin saja",
        "awannya akan hilang nanti."
      ],
      "name": "Ōgaki Chiaki",
      "msgidx": 3,
      "voice": "CHI_0140_0003",
      "vid": "VID_CHI",
      "value": "",
      "said": ""
    },
    {
      "function": "XWCR",
      "argument": [],
      "name": "",
      "msgidx": -1,
      "voice": "",
      "vid": "",
      "value": "",
      "said": ""
    },
    {
      "function": "XCUTINSET",
      "argument": [
        "R1",
        "1",
        "NAD_HPY",
        "0",
        "-1",
        "-1",
        "NONE",
        "T_OFF",
        "A_HANE",
        "CutinActive.V_ON"
      ],
      "name": "",
      "msgidx": -1,
      "voice": "",
      "vid": "",
      "value": "",
      "said": ""
    },
    {
      "function": "XCUTINDRAW",
      "argument": [],
      "name": "",
      "msgidx": -1,
      "voice": "",
      "vid": "",
      "value": "",
      "said": ""
    },
    {
      "function": "XMESS",
      "argument": [
        "Semuanyaー, cepatlaーh!"
      ],
      "name": "Kagamihara Nadeshiko",
      "msgidx": 4,
      "voice": "NAD_0203_0004",
      "vid": "VID_NAD",
      "value": "",
      "said": ""
    },
    {
      "function": "XWCR",
      "argument": [],
      "name": "",
      "msgidx": -1,
      "voice": "",
      "vid": "",
      "value": "",
      "said": ""
    },
    {
      "function": "XLCYDRAW",
      "argument": [
        "XLCYLOAD,Lucy.Type.BUST,BU_OFF",
        "XLCYLOAD,Lucy.Type.AUTO,SP_RIN_CMP1_0_SUP",
        "XLCYFADE,0,0.25"
      ],
      "name": "",
      "msgidx": -1,
      "voice": "",
      "vid": "",
      "value": "",
      "said": ""
    },
    {
      "function": "XMESS",
      "argument": [
        "Nadeshiko?",
        "Sudah sejauh itu."
      ],
      "name": "Shima Rin（Non-Voiced）",
      "msgidx": 5,
      "voice": "",
      "vid": "",
      "value": "",
      "said": ""
    },
    {
      "function": "XWCR",
      "argument": [],
      "name": "",
      "msgidx": -1,
      "voice": "",
      "vid": "",
      "value": "",
      "said": ""
    },
    {
      "function": "XCUTINCLEAR",
      "argument": [
        "4"
      ],
      "name": "",
      "msgidx": -1,
      "voice": "",
      "vid": "",
      "value": "",
      "said": ""
    },
    {
      "function": "XLCYDRAW",
      "argument": [
        "XLCYLOAD,Lucy.Type.BUST,BU_OFF",
        "XLCYLOAD,Lucy.Type.AUTO,SP_CHI_CMP_0_SUP",
        "XLCYFADE,0,0.25"
      ],
      "name": "",
      "msgidx": -1,
      "voice": "",
      "vid": "",
      "value": "",
      "said": ""
    },
    {
      "function": "XMESS",
      "argument": [
        "Grrr!",
        "Takkan kubiarkan tertinggal!"
      ],
      "name": "Ōgaki Chiaki",
      "msgidx": 6,
      "voice": "CHI_0141_0005",
      "vid": "VID_CHI",
      "value": "",
      "said": ""
    },
    {
      "function": "XWCR",
      "argument": [],
      "name": "",
      "msgidx": -1,
      "voice": "",
      "vid": "",
      "value": "",
      "said": ""
    },
    {
      "function": "XLCYDRAW",
      "argument": [
        "XLCYLOAD,Lucy.Type.BUST,BU_OFF",
        "XLCYLOAD,Lucy.Type.AUTO,SP_CHI_CMP_0_SER",
        "XLCYFADE,0,0.25"
      ],
      "name": "",
      "msgidx": -1,
      "voice": "",
      "vid": "",
      "value": "",
      "said": ""
    },
    {
      "function": "XMESS",
      "argument": [
        "Shimarin, Inuko!",
        "Ikuti akuー!"
      ],
      "name": "Ōgaki Chiaki",
      "msgidx": 7,
      "voice": "CHI_0142_0006",
      "vid": "VID_CHI",
      "value": "",
      "said": ""
    },
    {
      "function": "XWCR",
      "argument": [],
      "name": "",
      "msgidx": -1,
      "voice": "",
      "vid": "",
      "value": "",
      "said": ""
    },
    {
      "function": "XLCYDRAW",
      "argument": [
        "XLCYLOAD,Lucy.Type.BUST,BU_OFF",
        "XLCYLOAD,Lucy.Type.AUTO,SP_RIN_CMP1_0_SML",
        "XLCYFADE,0,0.25"
      ],
      "name": "",
      "msgidx": -1,
      "voice": "",
      "vid": "",
      "value": "",
      "said": ""
    },
    {
      "function": "XMESS",
      "argument": [
        "Dasar orang-orang ceria."
      ],
      "name": "Shima Rin（Non-Voiced）",
      "msgidx": 8,
      "voice": "",
      "vid": "",
      "value": "",
      "said": ""
    },
    {
      "function": "XWCR",
      "argument": [],
      "name": "",
      "msgidx": -1,
      "voice": "",
      "vid": "",
      "value": "",
      "said": ""
    },
    {
      "function": "XLCYDRAW",
      "argument": [
        "XLCYLOAD,Lucy.Type.BUST,BU_OFF",
        "XLCYLOAD,Lucy.Type.AUTO,SP_MIN_CMM_0_SUP",
        "XLCYFADE,0,0.25"
      ],
      "name": "",
      "msgidx": -1,
      "voice": "",
      "vid": "",
      "value": "",
      "said": ""
    },
    {
      "function": "XMESS",
      "argument": [
        "Semuanyaー!",
        "Perhatikan langkah kalian yaー!"
      ],
      "name": "Toba Minami",
      "msgidx": 9,
      "voice": "MIN_0085_0007",
      "vid": "VID_MIN",
      "value": "",
      "said": ""
    },
    {
      "function": "XWCR",
      "argument": [],
      "name": "",
      "msgidx": -1,
      "voice": "",
      "vid": "",
      "value": "",
      "said": ""
    },
    {
      "function": "XFADE",
      "argument": [
        "XFTS,MaskTexture.None,0",
        "XFOT,0.5"
      ],
      "name": "",
      "msgidx": -1,
      "voice": "",
      "vid": "",
      "value": "",
      "said": ""
    },
    {
      "function": "XWXB",
      "argument": [],
      "name": "",
      "msgidx": -1,
      "voice": "",
      "vid": "",
      "value": "",
      "said": ""
    },
    {
      "function": "SNSE",
      "argument": [
        "NSE_OFF",
        "0"
      ],
      "name": "",
      "msgidx": -1,
      "voice": "",
      "vid": "",
      "value": "",
      "said": ""
    },
    {
      "function": "XWXB",
      "argument": [],
      "name": "",
      "msgidx": -1,
      "voice": "",
      "vid": "",
      "value": "",
      "said": ""
    },
    {
      "function": "XLCYDRAW",
      "argument": [
        "XLCYLOAD,Lucy.Type.BACK,BG_156_A0",
        "XLCYFADE,0,0.001"
      ],
      "name": "",
      "msgidx": -1,
      "voice": "",
      "vid": "",
      "value": "",
      "said": ""
    },
    {
      "function": "XLCYDRAW",
      "argument": [
        "XLCYFIND,FindType.SP_C",
        "XLCYLOAD,Lucy.Type.BUST,BU_OFF",
        "XLCYLOAD,Lucy.Type.SP_L,SP_OFF",
        "XLCYLOAD,Lucy.Type.SP_R,SP_OFF",
        "XLCYLOAD,Lucy.Type.SP_C,SP_RIN_CMP1_0_SER",
        "XLCYFADE,0,0.25"
      ],
      "name": "",
      "msgidx": -1,
      "voice": "",
      "vid": "",
      "value": "",
      "said": ""
    },
    {
      "function": "SBGM",
      "argument": [
        "BGM_06"
      ],
      "name": "",
      "msgidx": -1,
      "voice": "",
      "vid": "",
      "value": "",
      "said": ""
    },
    {
      "function": "SESE",
      "argument": [
        "ESE_OFF",
        "0"
      ],
      "name": "",
      "msgidx": -1,
      "voice": "",
      "vid": "",
      "value": "",
      "said": ""
    },
    {
      "function": "XMON",
      "argument": [],
      "name": "",
      "msgidx": -1,
      "voice": "",
      "vid": "",
      "value": "",
      "said": ""
    },
    {
      "function": "XFADE",
      "argument": [
        "XFTS,MaskTexture.None,0",
        "XFIN,0.5"
      ],
      "name": "",
      "msgidx": -1,
      "voice": "",
      "vid": "",
      "value": "",
      "said": ""
    },
    {
      "function": "XMESS",
      "argument": [
        "Haa... Berat juga ya."
      ],
      "name": "Shima Rin（Non-Voiced）",
      "msgidx": 10,
      "voice": "",
      "vid": "",
      "value": "",
      "said": ""
    },
    {
      "function": "XWCR",
      "argument": [],
      "name": "",
      "msgidx": -1,
      "voice": "",
      "vid": "",
      "value": "",
      "said": ""
    },
    {
      "function": "XMESS",
      "argument": [
        "........."
      ],
      "name": "Ōgaki Chiaki",
      "msgidx": 11,
      "voice": "",
      "vid": "",
      "value": "",
      "said": ""
    },
    {
      "function": "XWCR",
      "argument": [],
      "name": "",
      "msgidx": -1,
      "voice": "",
      "vid": "",
      "value": "",
      "said": ""
    },
    {
      "function": "XLCYDRAW",
      "argument": [
        "XLCYLOAD,Lucy.Type.BUST,BU_OFF",
        "XLCYLOAD,Lucy.Type.AUTO,SP_RIN_CMP1_0_NML",
        "XLCYFADE,0,0.25"
      ],
      "name": "",
      "msgidx": -1,
      "voice": "",
      "vid": "",
      "value": "",
      "said": ""
    },
    {
      "function": "XMESS",
      "argument": [
        "Ōgaki, masih hidup?"
      ],
      "name": "Shima Rin（Non-Voiced）",
      "msgidx": 12,
      "voice": "",
      "vid": "",
      "value": "",
      "said": ""
    },
    {
      "function": "XWCR",
      "argument": [],
      "name": "",
      "msgidx": -1,
      "voice": "",
      "vid": "",
      "value": "",
      "said": ""
    },
    {
      "function": "XCUTINSET",
      "argument": [
        "L1",
        "2",
        "CHI_EXC",
        "0",
        "0",
        "-1",
        "NONE",
        "T_OFF",
        "A_KAKU",
        "CutinActive.V_ON"
      ],
      "name": "",
      "msgidx": -1,
      "voice": "",
      "vid": "",
      "value": "",
      "said": ""
    },
    {
      "function": "XCUTINDRAW",
      "argument": [],
      "name": "",
      "msgidx": -1,
      "voice": "",
      "vid": "",
      "value": "",
      "said": ""
    },
    {
      "function": "XMESS",
      "argument": [
        "Mungkin..."
      ],
      "name": "Ōgaki Chiaki",
      "msgidx": 13,
      "voice": "CHI_0143_0008",
      "vid": "VID_CHI",
      "value": "",
      "said": ""
    },
    {
      "function": "XWCR",
      "argument": [],
      "name": "",
      "msgidx": -1,
      "voice": "",
      "vid": "",
      "value": "",
      "said": ""
    },
    {
      "function": "XLCYDRAW",
      "argument": [
        "XLCYLOAD,Lucy.Type.BUST,BU_OFF",
        "XLCYLOAD,Lucy.Type.AUTO,SP_RIN_CMP1_0_CON",
        "XLCYFADE,0,0.25"
      ],
      "name": "",
      "msgidx": -1,
      "voice": "",
      "vid": "",
      "value": "",
      "said": ""
    },
    {
      "function": "XMESS",
      "argument": [
        "（Ternyata staminanya tidak",
        "　sebanyak yang kukira）"
      ],
      "name": "Shima Rin（Non-Voiced）",
      "msgidx": 14,
      "voice": "",
      "vid": "",
      "value": "",
      "said": ""
    },
    {
      "function": "XWCR",
      "argument": [],
      "name": "",
      "msgidx": -1,
      "voice": "",
      "vid": "",
      "value": "",
      "said": ""
    },
    {
      "function": "XFADE",
      "argument": [
        "XFTS,MaskTexture.None,0",
        "XFOT,0.5"
      ],
      "name": "",
      "msgidx": -1,
      "voice": "",
      "vid": "",
      "value": "",
      "said": ""
    },
    {
      "function": "XWXB",
      "argument": [],
      "name": "",
      "msgidx": -1,
      "voice": "",
      "vid": "",
      "value": "",
      "said": ""
    },
    {
      "function": "SNSE",
      "argument": [
        "NSE_OFF",
        "0"
      ],
      "name": "",
      "msgidx": -1,
      "voice": "",
      "vid": "",
      "value": "",
      "said": ""
    },
    {
      "function": "XWXB",
      "argument": [],
      "name": "",
      "msgidx": -1,
      "voice": "",
      "vid": "",
      "value": "",
      "said": ""
    },
    {
      "function": "XLCYDRAW",
      "argument": [
        "XLCYLOAD,Lucy.Type.BACK,BG_189_A0",
        "XLCYFADE,0,0.001"
      ],
      "name": "",
      "msgidx": -1,
      "voice": "",
      "vid": "",
      "value": "",
      "said": ""
    },
    {
      "function": "XLCYDRAW",
      "argument": [
        "XLCYINIT",
        "XLCYFIND,FindType.SP_C",
        "XLCYLOAD,Lucy.Type.BUST,BU_OFF",
        "XLCYLOAD,Lucy.Type.SP_L,SP_OFF",
        "XLCYLOAD,Lucy.Type.SP_R,SP_OFF",
        "XLCYLOAD,Lucy.Type.SP_C,SP_OFF",
        "XLCYLOAD,Lucy.Type.MG_0,MG_OFF",
        "XLCYLOAD,Lucy.Type.MG_1,MG_OFF",
        "XLCYFADE,0,0.25"
      ],
      "name": "",
      "msgidx": -1,
      "voice": "",
      "vid": "",
      "value": "",
      "said": ""
    },
    {
      "function": "SBGM",
      "argument": [
        "BGM_SAME"
      ],
      "name": "",
      "msgidx": -1,
      "voice": "",
      "vid": "",
      "value": "",
      "said": ""
    },
    {
      "function": "SESE",
      "argument": [
        "ESE_OFF",
        "0"
      ],
      "name": "",
      "msgidx": -1,
      "voice": "",
      "vid": "",
      "value": "",
      "said": ""
    },
    {
      "function": "XMON",
      "argument": [],
      "name": "",
      "msgidx": -1,
      "voice": "",
      "vid": "",
      "value": "",
      "said": ""
    },
    {
      "function": "XFADE",
      "argument": [
        "XFTS,MaskTexture.None,0",
        "XFIN,0.5"
      ],
      "name": "",
      "msgidx": -1,
      "voice": "",
      "vid": "",
      "value": "",
      "said": ""
    },
    {
      "function": "XMESS",
      "argument": [
        "Fuuh... Sampai juga."
      ],
      "name": "Shima Rin（Non-Voiced）",
      "msgidx": 15,
      "voice": "",
      "vid": "",
      "value": "",
      "said": ""
    },
    {
      "function": "XWCR",
      "argument": [],
      "name": "",
      "msgidx": -1,
      "voice": "",
      "vid": "",
      "value": "",
      "said": ""
    },
    {
      "function": "XMESS",
      "argument": [
        "Ah...!"
      ],
      "name": "Shima Rin（Non-Voiced）",
      "msgidx": 16,
      "voice": "",
      "vid": "",
      "value": "",
      "said": ""
    },
    {
      "function": "XWCR",
      "argument": [],
      "name": "",
      "msgidx": -1,
      "voice": "",
      "vid": "",
      "value": "",
      "said": ""
    },
    {
      "function": "XFADE",
      "argument": [
        "XFTS,MaskTexture.None,0",
        "XFOT,0.5"
      ],
      "name": "",
      "msgidx": -1,
      "voice": "",
      "vid": "",
      "value": "",
      "said": ""
    },
    {
      "function": "XWXB",
      "argument": [],
      "name": "",
      "msgidx": -1,
      "voice": "",
      "vid": "",
      "value": "",
      "said": ""
    },
    {
      "function": "SNSE",
      "argument": [
        "NSE_OFF",
        "0"
      ],
      "name": "",
      "msgidx": -1,
      "voice": "",
      "vid": "",
      "value": "",
      "said": ""
    },
    {
      "function": "XWXB",
      "argument": [],
      "name": "",
      "msgidx": -1,
      "voice": "",
      "vid": "",
      "value": "",
      "said": ""
    },
    {
      "function": "XLCYDRAW",
      "argument": [
        "XLCYLOAD,Lucy.Type.BACK,BG_048_A0",
        "XLCYFADE,0,0.001"
      ],
      "name": "",
      "msgidx": -1,
      "voice": "",
      "vid": "",
      "value": "",
      "said": ""
    },
    {
      "function": "XLCYDRAW",
      "argument": [
        "XLCYINIT",
        "XLCYFIND,FindType.SP_C",
        "XLCYLOAD,Lucy.Type.BUST,BU_OFF",
        "XLCYLOAD,Lucy.Type.SP_L,SP_OFF",
        "XLCYLOAD,Lucy.Type.SP_R,SP_OFF",
        "XLCYLOAD,Lucy.Type.SP_C,SP_OFF",
        "XLCYLOAD,Lucy.Type.MG_0,MG_OFF",
        "XLCYLOAD,Lucy.Type.MG_1,MG_OFF",
        "XLCYFADE,0,0.25"
      ],
      "name": "",
      "msgidx": -1,
      "voice": "",
      "vid": "",
      "value": "",
      "said": ""
    },
    {
      "function": "SBGM",
      "argument": [
        "BGM_SAME"
      ],
      "name": "",
      "msgidx": -1,
      "voice": "",
      "vid": "",
      "value": "",
      "said": ""
    },
    {
      "function": "SESE",
      "argument": [
        "ESE_OFF",
        "0"
      ],
      "name": "",
      "msgidx": -1,
      "voice": "",
      "vid": "",
      "value": "",
      "said": ""
    },
    {
      "function": "XMON",
      "argument": [],
      "name": "",
      "msgidx": -1,
      "voice": "",
      "vid": "",
      "value": "",
      "said": ""
    },
    {
      "function": "XFADE",
      "argument": [
        "XFTS,MaskTexture.None,0",
        "XFIN,0.5"
      ],
      "name": "",
      "msgidx": -1,
      "voice": "",
      "vid": "",
      "value": "",
      "said": ""
    },
    {
      "function": "XCUTINSET",
      "argument": [
        "L2",
        "1",
        "NAD_SML",
        "0",
        "-1",
        "-1",
        "NONE",
        "T_OFF",
        "A_NON",
        "CutinActive.V_ON"
      ],
      "name": "",
      "msgidx": -1,
      "voice": "",
      "vid": "",
      "value": "",
      "said": ""
    },
    {
      "function": "XCUTINDRAW",
      "argument": [],
      "name": "",
      "msgidx": -1,
      "voice": "",
      "vid": "",
      "value": "",
      "said": ""
    },
    {
      "function": "XMESS",
      "argument": [
        "Lihat, Rin-chan!",
        "Gunung Fujinya terlihat jelas loh!"
      ],
      "name": "Kagamihara Nadeshiko",
      "msgidx": 17,
      "voice": "NAD_0204_0009",
      "vid": "VID_NAD",
      "value": "",
      "said": ""
    },
    {
      "function": "XWCR",
      "argument": [],
      "name": "",
      "msgidx": -1,
      "voice": "",
      "vid": "",
      "value": "",
      "said": ""
    },
    {
      "function": "XCUTINSET",
      "argument": [
        "L1",
        "0",
        "RIN_SML",
        "0",
        "-1",
        "-1",
        "NONE",
        "T_OFF",
        "A_NON",
        "CutinActive.V_ON"
      ],
      "name": "",
      "msgidx": -1,
      "voice": "",
      "vid": "",
      "value": "",
      "said": ""
    },
    {
      "function": "XCUTINDRAW",
      "argument": [],
      "name": "",
      "msgidx": -1,
      "voice": "",
      "vid": "",
      "value": "",
      "said": ""
    },
    {
      "function": "XMESS",
      "argument": [
        "Iya, syukurlah."
      ],
      "name": "Shima Rin（Non-Voiced）",
      "msgidx": 18,
      "voice": "",
      "vid": "",
      "value": "",
      "said": ""
    },
    {
      "function": "XWCR",
      "argument": [],
      "name": "",
      "msgidx": -1,
      "voice": "",
      "vid": "",
      "value": "",
      "said": ""
    },
    {
      "function": "XCUTINCLEAR",
      "argument": [
        "4"
      ],
      "name": "",
      "msgidx": -1,
      "voice": "",
      "vid": "",
      "value": "",
      "said": ""
    },
    {
      "function": "XCUTINSET",
      "argument": [
        "R1",
        "3",
        "AOI_NML",
        "0",
        "-1",
        "AOI_NML",
        "NONE",
        "T_OFF",
        "A_NON",
        "CutinActive.V_ON"
      ],
      "name": "",
      "msgidx": -1,
      "voice": "",
      "vid": "",
      "value": "",
      "said": ""
    },
    {
      "function": "XCUTINDRAW",
      "argument": [],
      "name": "",
      "msgidx": -1,
      "voice": "",
      "vid": "",
      "value": "",
      "said": ""
    },
    {
      "function": "XMESS",
      "argument": [
        "Sebelum tertutup awan lagi,",
        "kita harus mengabadikannya ya."
      ],
      "name": "Inuyama Aoi",
      "msgidx": 19,
      "voice": "AOI_0140_0010",
      "vid": "VID_AOI",
      "value": "",
      "said": ""
    },
    {
      "function": "XWCR",
      "argument": [],
      "name": "",
      "msgidx": -1,
      "voice": "",
      "vid": "",
      "value": "",
      "said": ""
    },
    {
      "function": "XCUTINSET",
      "argument": [
        "L1",
        "1",
        "NAD_SML",
        "0",
        "-1",
        "-1",
        "NONE",
        "T_OFF",
        "A_NON",
        "CutinActive.V_ON"
      ],
      "name": "",
      "msgidx": -1,
      "voice": "",
      "vid": "",
      "value": "",
      "said": ""
    },
    {
      "function": "XCUTINDRAW",
      "argument": [],
      "name": "",
      "msgidx": -1,
      "voice": "",
      "vid": "",
      "value": "",
      "said": ""
    },
    {
      "function": "XMESS",
      "argument": [
        "Iya, ayo kita foto bersama!"
      ],
      "name": "Kagamihara Nadeshiko",
      "msgidx": 20,
      "voice": "NAD_0205_0011",
      "vid": "VID_NAD",
      "value": "",
      "said": ""
    },
    {
      "function": "XWCR",
      "argument": [],
      "name": "",
      "msgidx": -1,
      "voice": "",
      "vid": "",
      "value": "",
      "said": ""
    },
    {
      "function": "XCUTINSET",
      "argument": [
        "L2",
        "5",
        "MIN_SML",
        "2",
        "0",
        "-1",
        "NONE",
        "T_OFF",
        "A_NON",
        "CutinActive.V_ON"
      ],
      "name": "",
      "msgidx": -1,
      "voice": "",
      "vid": "",
      "value": "",
      "said": ""
    },
    {
      "function": "XCUTINDRAW",
      "argument": [],
      "name": "",
      "msgidx": -1,
      "voice": "",
      "vid": "",
      "value": "",
      "said": ""
    },
    {
      "function": "XMESS",
      "argument": [
        "Kalau begitu, setelah Ōgaki-san",
        "tiba, ibu akan memotret ya."
      ],
      "name": "Toba Minami",
      "msgidx": 21,
      "voice": "MIN_0086_0012",
      "vid": "VID_MIN",
      "value": "",
      "said": ""
    },
    {
      "function": "XWCR",
      "argument": [],
      "name": "",
      "msgidx": -1,
      "voice": "",
      "vid": "",
      "value": "",
      "said": ""
    },
    {
      "function": "XCUTINCLEAR",
      "argument": [
        "4"
      ],
      "name": "",
      "msgidx": -1,
      "voice": "",
      "vid": "",
      "value": "",
      "said": ""
    },
    {
      "function": "XMESS",
      "argument": [
        "（Ramai ya...",
        "　Yah, tidak buruk juga sih）"
      ],
      "name": "Shima Rin（Non-Voiced）",
      "msgidx": 22,
      "voice": "",
      "vid": "",
      "value": "",
      "said": ""
    },
    {
      "function": "XWAI",
      "argument": [],
      "name": "",
      "msgidx": -1,
      "voice": "",
      "vid": "",
      "value": "",
      "said": ""
    },
    {
      "function": "XFADE",
      "argument": [
        "XFED,0.5"
      ],
      "name": "",
      "msgidx": -1,
      "voice": "",
      "vid": "",
      "value": "",
      "said": ""
    },
    {
      "function": "XCLR",
      "argument": [],
      "name": "",
      "msgidx": -1,
      "voice": "",
      "vid": "",
      "value": "",
      "said": ""
    },
    {
      "function": "XEOS",
      "argument": [],
      "name": "",
      "msgidx": -1,
      "voice": "",
      "vid": "",
      "value": "",
      "said": ""
    }
  ]
}